{"bodies":[{"childs":[{"color":"7a7a7a","joints":[{"id":7102},{"id":7104}],"pos":{"x":-8,"y":-10,"z":1},"shapeId":"8024db09-9147-4fe3-a747-00bc30ab724b","xaxis":-1,"zaxis":-2}]},{"childs":[{"color":"7a7a7a","joints":[{"id":7100},{"id":7099}],"pos":{"x":-10,"y":11,"z":1},"shapeId":"8024db09-9147-4fe3-a747-00bc30ab724b","xaxis":-1,"zaxis":-2}]},{"childs":[{"bounds":{"x":1,"y":1,"z":1},"color":"675f51","pos":{"x":-2,"y":-9,"z":7},"shapeId":"8aedf6c2-94e1-4506-89d4-a0227c552f1e","xaxis":1,"zaxis":3},{"bounds":{"x":1,"y":1,"z":1},"color":"675f51","joints":[{"id":7115}],"pos":{"x":-14,"y":-9,"z":7},"shapeId":"8aedf6c2-94e1-4506-89d4-a0227c552f1e","xaxis":1,"zaxis":3},{"bounds":{"x":1,"y":1,"z":3},"color":"675f51","pos":{"x":-7,"y":-10,"z":4},"shapeId":"8aedf6c2-94e1-4506-89d4-a0227c552f1e","xaxis":1,"zaxis":3},{"bounds":{"x":1,"y":1,"z":3},"color":"675f51","pos":{"x":-9,"y":-10,"z":4},"shapeId":"8aedf6c2-94e1-4506-89d4-a0227c552f1e","xaxis":1,"zaxis":3},{"bounds":{"x":13,"y":1,"z":1},"color":"675f51","pos":{"x":-14,"y":-9,"z":6},"shapeId":"8aedf6c2-94e1-4506-89d4-a0227c552f1e","xaxis":1,"zaxis":3},{"bounds":{"x":1,"y":1,"z":1},"color":"675f51","joints":[{"id":7107}],"pos":{"x":-8,"y":-9,"z":5},"shapeId":"8aedf6c2-94e1-4506-89d4-a0227c552f1e","xaxis":1,"zaxis":3},{"bounds":{"x":1,"y":1,"z":3},"color":"675f51","pos":{"x":-7,"y":-8,"z":4},"shapeId":"8aedf6c2-94e1-4506-89d4-a0227c552f1e","xaxis":1,"zaxis":3},{"bounds":{"x":1,"y":1,"z":3},"color":"675f51","pos":{"x":-9,"y":-8,"z":4},"shapeId":"8aedf6c2-94e1-4506-89d4-a0227c552f1e","xaxis":1,"zaxis":3}]},{"childs":[{"color":"7a7a7a","joints":[{"id":7105},{"id":7103}],"pos":{"x":-7,"y":-11,"z":1},"shapeId":"8024db09-9147-4fe3-a747-00bc30ab724b","xaxis":1,"zaxis":2}]},{"childs":[{"color":"7a7a7a","joints":[{"id":7100}],"pos":{"x":-11,"y":10,"z":0},"shapeId":"0dba257b-b907-4919-baaf-2fefe19f4e24","xaxis":-1,"zaxis":2},{"color":"7a7a7a","pos":{"x":-12,"y":10,"z":0},"shapeId":"0dba257b-b907-4919-baaf-2fefe19f4e24","xaxis":-1,"zaxis":2},{"color":"df7f01","pos":{"x":-13,"y":8,"z":-2},"shapeId":"db66f0b1-0c50-4b74-bdc7-771374204b1f","xaxis":3,"zaxis":-1}]},{"childs":[{"color":"7a7a7a","joints":[{"id":7098},{"id":7101}],"pos":{"x":-5,"y":10,"z":1},"shapeId":"8024db09-9147-4fe3-a747-00bc30ab724b","xaxis":1,"zaxis":2}]},{"childs":[{"color":"7a7a7a","joints":[{"id":7102}],"pos":{"x":-9,"y":-11,"z":0},"shapeId":"0dba257b-b907-4919-baaf-2fefe19f4e24","xaxis":-1,"zaxis":2},{"color":"7a7a7a","pos":{"x":-10,"y":-11,"z":0},"shapeId":"0dba257b-b907-4919-baaf-2fefe19f4e24","xaxis":-1,"zaxis":2},{"color":"7a7a7a","pos":{"x":-11,"y":-11,"z":0},"shapeId":"0dba257b-b907-4919-baaf-2fefe19f4e24","xaxis":-1,"zaxis":2},{"color":"7a7a7a","pos":{"x":-12,"y":-11,"z":0},"shapeId":"0dba257b-b907-4919-baaf-2fefe19f4e24","xaxis":-1,"zaxis":2},{"color":"df7f01","pos":{"x":-13,"y":-13,"z":-2},"shapeId":"db66f0b1-0c50-4b74-bdc7-771374204b1f","xaxis":3,"zaxis":-1}]},{"childs":[{"bounds":{"x":1,"y":1,"z":1},"color":"675f51","joints":[{"id":7106},{"id":7107}],"pos":{"x":-8,"y":-9,"z":4},"shapeId":"8aedf6c2-94e1-4506-89d4-a0227c552f1e","xaxis":1,"zaxis":3}]},{"childs":[{"color":"7a7a7a","joints":[{"id":7096}],"pos":{"x":-8,"y":10,"z":4},"shapeId":"0dba257b-b907-4919-baaf-2fefe19f4e24","xaxis":-3,"zaxis":2},{"color":"7a7a7a","pos":{"x":-8,"y":11,"z":3},"shapeId":"8024db09-9147-4fe3-a747-00bc30ab724b","xaxis":-1,"zaxis":-2},{"color":"7a7a7a","pos":{"x":-9,"y":11,"z":2},"shapeId":"8024db09-9147-4fe3-a747-00bc30ab724b","xaxis":3,"zaxis":-2},{"color":"7a7a7a","pos":{"x":-9,"y":11,"z":3},"shapeId":"0dba257b-b907-4919-baaf-2fefe19f4e24","xaxis":3,"zaxis":-2},{"color":"7a7a7a","pos":{"x":-9,"y":10,"z":4},"shapeId":"8024db09-9147-4fe3-a747-00bc30ab724b","xaxis":-1,"zaxis":2},{"color":"7a7a7a","joints":[{"id":7099}],"pos":{"x":-10,"y":10,"z":5},"shapeId":"8024db09-9147-4fe3-a747-00bc30ab724b","xaxis":-3,"zaxis":2}]},{"childs":[{"color":"df7f01","controller":{"containers":[{"container":[{"quantity":0,"uuid":"00000000-0000-0000-0000-000000000000"}],"filters":[{"uuid":"910a7f2c-52b0-46eb-8873-ad13255539af"}],"id":0,"slots":1,"stackSize":10}],"controllers":null,"data":"8CBMVUEAAAABBQAAAAICAAAABoBiYXR0ZXJ5UG9pbnRzCAAEAAAAB2dlYXJJZHgIAg","id":39545,"joints":[{"id":7115,"reverse":0}]},"pos":{"x":-6,"y":-3,"z":4},"shapeId":"5e5d231e-405e-4f45-9bd0-b3557dbb42eb","xaxis":-2,"zaxis":-1},{"bounds":{"x":1,"y":6,"z":1},"color":"675f51","pos":{"x":-8,"y":6,"z":5},"shapeId":"8aedf6c2-94e1-4506-89d4-a0227c552f1e","xaxis":1,"zaxis":3},{"bounds":{"x":1,"y":7,"z":1},"color":"675f51","pos":{"x":-7,"y":5,"z":5},"shapeId":"8aedf6c2-94e1-4506-89d4-a0227c552f1e","xaxis":1,"zaxis":3},{"bounds":{"x":1,"y":7,"z":1},"color":"675f51","pos":{"x":-9,"y":5,"z":5},"shapeId":"8aedf6c2-94e1-4506-89d4-a0227c552f1e","xaxis":1,"zaxis":3},{"color":"1c8687","pos":{"x":-9,"y":16,"z":2},"shapeId":"9f37d9e9-be8d-49c8-a7ac-e59c67786083","xaxis":-3,"zaxis":2},{"bounds":{"x":1,"y":3,"z":1},"color":"675f51","pos":{"x":-13,"y":-10,"z":4},"shapeId":"8aedf6c2-94e1-4506-89d4-a0227c552f1e","xaxis":1,"zaxis":3},{"color":"c36512","controller":{"color":"c36512","coneAngle":0,"controllers":null,"id":39214,"joints":null,"luminance":40},"pos":{"x":-10,"y":16,"z":4},"shapeId":"695d66c8-b937-472d-8bc2-f3d72dd92879","xaxis":-1,"zaxis":2},{"bounds":{"x":3,"y":10,"z":1},"color":"675f51","pos":{"x":-6,"y":6,"z":5},"shapeId":"8aedf6c2-94e1-4506-89d4-a0227c552f1e","xaxis":1,"zaxis":3},{"color":"7a7a7a","pos":{"x":-6,"y":12,"z":5},"shapeId":"fef41dd6-3624-4983-862e-aa9c04330afd","xaxis":-1,"zaxis":2},{"color":"7a7a7a","pos":{"x":-7,"y":12,"z":5},"shapeId":"fef41dd6-3624-4983-862e-aa9c04330afd","xaxis":-1,"zaxis":2},{"color":"7a7a7a","pos":{"x":-8,"y":12,"z":5},"shapeId":"fef41dd6-3624-4983-862e-aa9c04330afd","xaxis":-1,"zaxis":2},{"color":"909090","controller":{"controllers":null,"gear":1,"id":39207,"joints":[{"id":7100,"reverse":1},{"id":7101,"reverse":0},{"id":7103,"reverse":0},{"id":7102,"reverse":1}]},"pos":{"x":-6,"y":5,"z":3},"shapeId":"1018aabd-5494-11e6-beb8-9e71128cae77","xaxis":-1,"zaxis":2},{"bounds":{"x":1,"y":9,"z":2},"color":"675f51","pos":{"x":-13,"y":6,"z":4},"shapeId":"8aedf6c2-94e1-4506-89d4-a0227c552f1e","xaxis":1,"zaxis":3},{"bounds":{"x":3,"y":4,"z":1},"color":"675f51","joints":[{"id":7096},{"id":7097}],"pos":{"x":-9,"y":9,"z":4},"shapeId":"8aedf6c2-94e1-4506-89d4-a0227c552f1e","xaxis":1,"zaxis":3},{"bounds":{"x":1,"y":9,"z":2},"color":"675f51","pos":{"x":-3,"y":6,"z":4},"shapeId":"8aedf6c2-94e1-4506-89d4-a0227c552f1e","xaxis":1,"zaxis":3},{"bounds":{"x":2,"y":1,"z":4},"color":"675f51","pos":{"x":-12,"y":15,"z":1},"shapeId":"8aedf6c2-94e1-4506-89d4-a0227c552f1e","xaxis":1,"zaxis":3},{"bounds":{"x":4,"y":1,"z":3},"color":"675f51","pos":{"x":-6,"y":5,"z":3},"shapeId":"8aedf6c2-94e1-4506-89d4-a0227c552f1e","xaxis":1,"zaxis":3},{"bounds":{"x":11,"y":1,"z":3},"color":"675f51","pos":{"x":-13,"y":4,"z":3},"shapeId":"8aedf6c2-94e1-4506-89d4-a0227c552f1e","xaxis":1,"zaxis":3},{"bounds":{"x":4,"y":13,"z":1},"color":"675f51","pos":{"x":-6,"y":-7,"z":2},"shapeId":"8aedf6c2-94e1-4506-89d4-a0227c552f1e","xaxis":1,"zaxis":3},{"bounds":{"x":1,"y":2,"z":2},"color":"675f51","pos":{"x":-3,"y":6,"z":2},"shapeId":"8aedf6c2-94e1-4506-89d4-a0227c552f1e","xaxis":1,"zaxis":3},{"bounds":{"x":1,"y":2,"z":2},"color":"675f51","pos":{"x":-13,"y":6,"z":2},"shapeId":"8aedf6c2-94e1-4506-89d4-a0227c552f1e","xaxis":1,"zaxis":3},{"bounds":{"x":9,"y":3,"z":1},"color":"675f51","pos":{"x":-12,"y":-10,"z":2},"shapeId":"8aedf6c2-94e1-4506-89d4-a0227c552f1e","xaxis":1,"zaxis":3},{"bounds":{"x":5,"y":1,"z":1},"color":"675f51","pos":{"x":-10,"y":15,"z":1},"shapeId":"8aedf6c2-94e1-4506-89d4-a0227c552f1e","xaxis":1,"zaxis":3},{"bounds":{"x":2,"y":1,"z":4},"color":"675f51","pos":{"x":-5,"y":15,"z":1},"shapeId":"8aedf6c2-94e1-4506-89d4-a0227c552f1e","xaxis":1,"zaxis":3},{"bounds":{"x":9,"y":1,"z":2},"color":"675f51","pos":{"x":-12,"y":-14,"z":2},"shapeId":"8aedf6c2-94e1-4506-89d4-a0227c552f1e","xaxis":1,"zaxis":3},{"color":"df7f01","controller":{"active":false,"controllers":[{"id":39214},{"id":39209}],"id":39208,"joints":null},"pos":{"x":-7,"y":4,"z":5},"shapeId":"7cf717d7-d167-4f2d-a6e7-6b2c70aa3986","xaxis":-1,"zaxis":3},{"color":"ed541b","pos":{"x":-5,"y":17,"z":0},"shapeId":"a5198434-2639-4cb0-8e01-865bc4d9b791","xaxis":-1,"zaxis":2},{"bounds":{"x":9,"y":7,"z":1},"color":"675f51","joints":[{"id":7106}],"pos":{"x":-12,"y":-10,"z":3},"shapeId":"8aedf6c2-94e1-4506-89d4-a0227c552f1e","xaxis":1,"zaxis":3},{"bounds":{"x":3,"y":2,"z":4},"color":"675f51","pos":{"x":-9,"y":13,"z":1},"shapeId":"8aedf6c2-94e1-4506-89d4-a0227c552f1e","xaxis":1,"zaxis":3},{"bounds":{"x":4,"y":1,"z":3},"color":"675f51","pos":{"x":-13,"y":5,"z":3},"shapeId":"8aedf6c2-94e1-4506-89d4-a0227c552f1e","xaxis":1,"zaxis":3},{"bounds":{"x":5,"y":1,"z":3},"color":"888888","pos":{"x":-10,"y":15,"z":2},"shapeId":"3d0b7a6e-5b40-474c-bbaf-efaa54890e6a","xaxis":1,"zaxis":3},{"color":"c36512","controller":{"color":"c36512","coneAngle":0,"controllers":null,"id":39209,"joints":null,"luminance":100},"pos":{"x":-3,"y":16,"z":4},"shapeId":"695d66c8-b937-472d-8bc2-f3d72dd92879","xaxis":-1,"zaxis":2},{"bounds":{"x":3,"y":10,"z":1},"color":"675f51","pos":{"x":-12,"y":6,"z":5},"shapeId":"8aedf6c2-94e1-4506-89d4-a0227c552f1e","xaxis":1,"zaxis":3},{"color":"1c8687","pos":{"x":-8,"y":17,"z":1},"shapeId":"9f37d9e9-be8d-49c8-a7ac-e59c67786083","xaxis":3,"zaxis":-2},{"bounds":{"x":1,"y":3,"z":2},"color":"675f51","pos":{"x":-3,"y":-6,"z":3},"shapeId":"8aedf6c2-94e1-4506-89d4-a0227c552f1e","xaxis":1,"zaxis":3},{"bounds":{"x":10,"y":4,"z":1},"color":"675f51","joints":[{"id":7104},{"id":7105}],"pos":{"x":-13,"y":-14,"z":4},"shapeId":"8aedf6c2-94e1-4506-89d4-a0227c552f1e","xaxis":1,"zaxis":3},{"bounds":{"x":1,"y":4,"z":2},"color":"675f51","pos":{"x":-13,"y":-7,"z":3},"shapeId":"8aedf6c2-94e1-4506-89d4-a0227c552f1e","xaxis":1,"zaxis":3},{"bounds":{"x":1,"y":1,"z":1},"color":"675f51","pos":{"x":-3,"y":-7,"z":3},"shapeId":"8aedf6c2-94e1-4506-89d4-a0227c552f1e","xaxis":1,"zaxis":3},{"bounds":{"x":4,"y":13,"z":1},"color":"675f51","pos":{"x":-13,"y":-7,"z":2},"shapeId":"8aedf6c2-94e1-4506-89d4-a0227c552f1e","xaxis":1,"zaxis":3},{"color":"df7f01","controller":{"containers":null,"controllers":[{"id":39208},{"id":39207},{"id":39212}],"id":39210,"joints":[{"id":7097,"reverse":1},{"id":7096,"reverse":1}],"steering":[{"id":7097,"leftAngleLimit":27.0,"leftAngleSpeed":4.244132041931152,"rightAngleLimit":27.0,"rightAngleSpeed":4.244132041931152,"unlocked":true},{"id":7096,"leftAngleLimit":27.0,"leftAngleSpeed":4.244132041931152,"rightAngleLimit":27.0,"rightAngleSpeed":4.244132041931152,"unlocked":true}]},"pos":{"x":-8,"y":-2,"z":3},"shapeId":"ffa3a47e-fc0d-4977-802f-bd15683bbe5c","xaxis":-1,"zaxis":2},{"bounds":{"x":1,"y":2,"z":3},"color":"675f51","pos":{"x":-3,"y":-3,"z":3},"shapeId":"8aedf6c2-94e1-4506-89d4-a0227c552f1e","xaxis":1,"zaxis":3},{"bounds":{"x":9,"y":1,"z":3},"color":"675f51","pos":{"x":-12,"y":-3,"z":3},"shapeId":"8aedf6c2-94e1-4506-89d4-a0227c552f1e","xaxis":1,"zaxis":3},{"color":"df7f00","controller":{"containers":null,"controllers":null,"id":39212,"joints":null},"pos":{"x":-12,"y":5,"z":6},"shapeId":"3007aaaf-5494-11e6-beb8-9e71128cae77","xaxis":1,"zaxis":-2},{"color":"df7f00","controller":{"containers":null,"controllers":null,"id":39213,"joints":null},"pos":{"x":-6,"y":5,"z":6},"shapeId":"3007aaaf-5494-11e6-beb8-9e71128cae77","xaxis":1,"zaxis":-2},{"bounds":{"x":3,"y":1,"z":2},"color":"8d8f89","pos":{"x":-9,"y":4,"z":6},"shapeId":"873533c3-2574-4d97-8a2d-a108209054ba","xaxis":1,"zaxis":3},{"bounds":{"x":1,"y":1,"z":1},"color":"8d8f89","pos":{"x":-3,"y":3,"z":7},"shapeId":"873533c3-2574-4d97-8a2d-a108209054ba","xaxis":1,"zaxis":3},{"bounds":{"x":1,"y":1,"z":2},"color":"8d8f89","pos":{"x":-3,"y":4,"z":6},"shapeId":"873533c3-2574-4d97-8a2d-a108209054ba","xaxis":1,"zaxis":3},{"bounds":{"x":3,"y":1,"z":1},"color":"8d8f89","pos":{"x":-6,"y":4,"z":7},"shapeId":"873533c3-2574-4d97-8a2d-a108209054ba","xaxis":1,"zaxis":3},{"bounds":{"x":3,"y":1,"z":1},"color":"8d8f89","pos":{"x":-12,"y":4,"z":7},"shapeId":"873533c3-2574-4d97-8a2d-a108209054ba","xaxis":1,"zaxis":3},{"bounds":{"x":1,"y":1,"z":1},"color":"8d8f89","pos":{"x":-13,"y":4,"z":6},"shapeId":"873533c3-2574-4d97-8a2d-a108209054ba","xaxis":1,"zaxis":3},{"bounds":{"x":11,"y":1,"z":1},"color":"8d8f89","pos":{"x":-13,"y":3,"z":8},"shapeId":"873533c3-2574-4d97-8a2d-a108209054ba","xaxis":1,"zaxis":3},{"bounds":{"x":1,"y":1,"z":1},"color":"8d8f89","pos":{"x":-13,"y":3,"z":7},"shapeId":"873533c3-2574-4d97-8a2d-a108209054ba","xaxis":1,"zaxis":3},{"color":"1c8687","pos":{"x":-10,"y":16,"z":2},"shapeId":"9f37d9e9-be8d-49c8-a7ac-e59c67786083","xaxis":-3,"zaxis":2},{"color":"565656","pos":{"x":-11,"y":16,"z":1},"shapeId":"4f1c0036-389b-432e-81de-8261cb9f9d57","xaxis":3,"zaxis":-1},{"color":"565656","pos":{"x":-4,"y":16,"z":2},"shapeId":"4f1c0036-389b-432e-81de-8261cb9f9d57","xaxis":-3,"zaxis":1},{"bounds":{"x":1,"y":8,"z":1},"color":"675f51","pos":{"x":-3,"y":-14,"z":4},"shapeId":"8aedf6c2-94e1-4506-89d4-a0227c552f1e","xaxis":1,"zaxis":3},{"color":"1c8687","pos":{"x":-7,"y":17,"z":1},"shapeId":"9f37d9e9-be8d-49c8-a7ac-e59c67786083","xaxis":3,"zaxis":-2},{"bounds":{"x":1,"y":2,"z":3},"color":"675f51","pos":{"x":-13,"y":-3,"z":3},"shapeId":"8aedf6c2-94e1-4506-89d4-a0227c552f1e","xaxis":1,"zaxis":3},{"color":"1c8687","pos":{"x":-5,"y":16,"z":2},"shapeId":"9f37d9e9-be8d-49c8-a7ac-e59c67786083","xaxis":-3,"zaxis":2},{"bounds":{"x":3,"y":14,"z":1},"color":"675f51","pos":{"x":-9,"y":-7,"z":2},"shapeId":"8aedf6c2-94e1-4506-89d4-a0227c552f1e","xaxis":1,"zaxis":3},{"color":"1c8687","pos":{"x":-6,"y":17,"z":1},"shapeId":"9f37d9e9-be8d-49c8-a7ac-e59c67786083","xaxis":3,"zaxis":-2},{"color":"1c8687","pos":{"x":-4,"y":16,"z":2},"shapeId":"9f37d9e9-be8d-49c8-a7ac-e59c67786083","xaxis":-3,"zaxis":2},{"color":"df7f01","controller":{"containers":null,"controllers":[{"id":39545},{"id":39551},{"id":39535},{"id":39528},{"id":39521},{"id":39514},{"id":39507}],"id":39779,"joints":null,"steering":null},"pos":{"x":-3,"y":-2,"z":3},"shapeId":"ffa3a47e-fc0d-4977-802f-bd15683bbe5c","xaxis":-1,"zaxis":2},{"color":"df7f01","controller":{"active":false,"controllers":[{"id":39768},{"id":39774},{"id":39785},{"id":39791},{"id":39797},{"id":39803}],"id":39812,"joints":null,"mode":1},"pos":{"x":-5,"y":-4,"z":4},"shapeId":"9f0f56e8-2c31-4d83-996c-d00a9b296c3f","xaxis":-1,"zaxis":2},{"color":"df7f01","controller":{"active":false,"controllers":[{"id":39769},{"id":39775},{"id":39783},{"id":39790},{"id":39796},{"id":39802}],"id":39813,"joints":null,"mode":1},"pos":{"x":-5,"y":-5,"z":4},"shapeId":"9f0f56e8-2c31-4d83-996c-d00a9b296c3f","xaxis":-1,"zaxis":2},{"color":"df7f01","controller":{"active":false,"controllers":[{"id":39763},{"id":39773},{"id":39786},{"id":39792},{"id":39798},{"id":39804}],"id":39814,"joints":null,"mode":1},"pos":{"x":-4,"y":-4,"z":4},"shapeId":"9f0f56e8-2c31-4d83-996c-d00a9b296c3f","xaxis":-1,"zaxis":2},{"color":"df7f01","controller":{"active":false,"controllers":[{"id":39772},{"id":39778},{"id":39780},{"id":39793},{"id":39799},{"id":39787}],"id":39815,"joints":null,"mode":1},"pos":{"x":-9,"y":-5,"z":4},"shapeId":"9f0f56e8-2c31-4d83-996c-d00a9b296c3f","xaxis":-1,"zaxis":2},{"color":"df7f01","controller":{"active":false,"controllers":[{"id":39770},{"id":39776},{"id":39782},{"id":39789},{"id":39795},{"id":39801}],"id":39816,"joints":null,"mode":1},"pos":{"x":-9,"y":-4,"z":4},"shapeId":"9f0f56e8-2c31-4d83-996c-d00a9b296c3f","xaxis":-1,"zaxis":2},{"color":"df7f01","controller":{"active":false,"controllers":[{"id":39771},{"id":39777},{"id":39781},{"id":39788},{"id":39794},{"id":39800}],"id":39817,"joints":null,"mode":1},"pos":{"x":-10,"y":-4,"z":4},"shapeId":"9f0f56e8-2c31-4d83-996c-d00a9b296c3f","xaxis":-1,"zaxis":2}]},{"childs":[{"color":"7a7a7a","joints":[{"id":7101}],"pos":{"x":-4,"y":11,"z":0},"shapeId":"0dba257b-b907-4919-baaf-2fefe19f4e24","xaxis":1,"zaxis":-2},{"color":"7a7a7a","pos":{"x":-3,"y":11,"z":0},"shapeId":"0dba257b-b907-4919-baaf-2fefe19f4e24","xaxis":1,"zaxis":-2},{"color":"df7f01","pos":{"x":-2,"y":13,"z":-2},"shapeId":"db66f0b1-0c50-4b74-bdc7-771374204b1f","xaxis":3,"zaxis":1}]},{"childs":[{"color":"df7f00","controller":{"controllers":null,"id":39811,"joints":null,"level":6},"pos":{"x":-3,"y":-4,"z":19},"shapeId":"c394b6e8-554c-4074-a119-ab2fec55e456","xaxis":3,"zaxis":2},{"color":"df7f00","controller":{"active":false,"controllers":[{"id":39811}],"id":39810,"joints":null},"pos":{"x":-2,"y":-5,"z":19},"shapeId":"70e5729d-0706-4c28-80a2-2ab9d7e7532c","xaxis":3,"zaxis":-1},{"color":"af0e0e","controller":{"containers":null,"controllers":null,"id":39809,"joints":null},"pos":{"x":-2,"y":-6,"z":19},"shapeId":"e1ae1714-b60c-41f9-afb9-6f916ec1f59b","xaxis":3,"zaxis":-1},{"color":"df7f01","controller":{"audioEnabled":false,"buttonMode":true,"color":"eeeeee","colorMode":false,"controllers":[{"id":39807}],"id":39808,"joints":null,"range":1},"pos":{"x":-2,"y":-11,"z":19},"shapeId":"1d4793af-cb66-4628-804a-9d7404712643","xaxis":3,"zaxis":-2},{"color":"df7f01","controller":{"active":false,"controllers":[{"id":39809}],"id":39807,"joints":null,"seconds":0,"ticks":1},"pos":{"x":-3,"y":-8,"z":20},"shapeId":"8f7fd0e7-c46e-4944-a414-7ce2437bb30f","xaxis":-3,"zaxis":1},{"color":"df7f01","controller":{"active":false,"controllers":null,"id":39806,"joints":null,"mode":0},"pos":{"x":-2,"y":-9,"z":20},"shapeId":"9f0f56e8-2c31-4d83-996c-d00a9b296c3f","xaxis":-3,"zaxis":-1},{"color":"404040","controller":{"containers":null,"controllers":null,"id":39805,"joints":null},"pos":{"x":-2,"y":-11,"z":20},"shapeId":"e65b6225-14f9-4d71-b8ed-245df3e04847","xaxis":2,"zaxis":-1},{"bounds":{"x":1,"y":1,"z":1},"color":"675f51","pos":{"x":-3,"y":-9,"z":19},"shapeId":"8aedf6c2-94e1-4506-89d4-a0227c552f1e","xaxis":1,"zaxis":3},{"color":"df7f00","controller":{"controllers":null,"id":39476,"joints":null,"level":6},"pos":{"x":-4,"y":-4,"z":19},"shapeId":"c394b6e8-554c-4074-a119-ab2fec55e456","xaxis":-1,"zaxis":2},{"color":"df7f00","controller":{"active":false,"controllers":[{"id":39476},{"id":39812}],"id":39475,"joints":null},"pos":{"x":-4,"y":-5,"z":20},"shapeId":"70e5729d-0706-4c28-80a2-2ab9d7e7532c","xaxis":-1,"zaxis":-3},{"color":"af0e0e","controller":{"containers":null,"controllers":null,"id":39474,"joints":null},"pos":{"x":-4,"y":-6,"z":20},"shapeId":"e1ae1714-b60c-41f9-afb9-6f916ec1f59b","xaxis":-1,"zaxis":-3},{"color":"df7f01","controller":{"audioEnabled":false,"buttonMode":true,"color":"eeeeee","colorMode":false,"controllers":[{"id":39472}],"id":39473,"joints":null,"range":1},"pos":{"x":-4,"y":-11,"z":20},"shapeId":"1d4793af-cb66-4628-804a-9d7404712643","xaxis":-1,"zaxis":-2},{"color":"df7f01","controller":{"active":false,"controllers":[{"id":39474}],"id":39472,"joints":null,"seconds":0,"ticks":1},"pos":{"x":-5,"y":-8,"z":19},"shapeId":"8f7fd0e7-c46e-4944-a414-7ce2437bb30f","xaxis":1,"zaxis":3},{"color":"df7f01","controller":{"active":false,"controllers":null,"id":39471,"joints":null,"mode":0},"pos":{"x":-5,"y":-9,"z":20},"shapeId":"9f0f56e8-2c31-4d83-996c-d00a9b296c3f","xaxis":1,"zaxis":-3},{"color":"404040","controller":{"containers":null,"controllers":null,"id":39470,"joints":null},"pos":{"x":-5,"y":-11,"z":20},"shapeId":"e65b6225-14f9-4d71-b8ed-245df3e04847","xaxis":2,"zaxis":-3},{"bounds":{"x":1,"y":1,"z":1},"color":"675f51","pos":{"x":-5,"y":-9,"z":19},"shapeId":"8aedf6c2-94e1-4506-89d4-a0227c552f1e","xaxis":1,"zaxis":3},{"color":"df7f00","controller":{"controllers":null,"id":39469,"joints":null,"level":6},"pos":{"x":-6,"y":-4,"z":19},"shapeId":"c394b6e8-554c-4074-a119-ab2fec55e456","xaxis":-1,"zaxis":2},{"color":"df7f00","controller":{"active":false,"controllers":[{"id":39469},{"id":39813}],"id":39468,"joints":null},"pos":{"x":-6,"y":-5,"z":20},"shapeId":"70e5729d-0706-4c28-80a2-2ab9d7e7532c","xaxis":-1,"zaxis":-3},{"color":"af0e0e","controller":{"containers":null,"controllers":null,"id":39467,"joints":null},"pos":{"x":-6,"y":-6,"z":20},"shapeId":"e1ae1714-b60c-41f9-afb9-6f916ec1f59b","xaxis":-1,"zaxis":-3},{"color":"df7f01","controller":{"audioEnabled":false,"buttonMode":true,"color":"eeeeee","colorMode":false,"controllers":[{"id":39465}],"id":39466,"joints":null,"range":1},"pos":{"x":-6,"y":-11,"z":20},"shapeId":"1d4793af-cb66-4628-804a-9d7404712643","xaxis":-1,"zaxis":-2},{"color":"df7f01","controller":{"active":false,"controllers":[{"id":39467}],"id":39465,"joints":null,"seconds":0,"ticks":1},"pos":{"x":-7,"y":-8,"z":19},"shapeId":"8f7fd0e7-c46e-4944-a414-7ce2437bb30f","xaxis":1,"zaxis":3},{"color":"df7f01","controller":{"active":false,"controllers":null,"id":39464,"joints":null,"mode":0},"pos":{"x":-7,"y":-9,"z":20},"shapeId":"9f0f56e8-2c31-4d83-996c-d00a9b296c3f","xaxis":1,"zaxis":-3},{"color":"404040","controller":{"containers":null,"controllers":null,"id":39463,"joints":null},"pos":{"x":-7,"y":-11,"z":20},"shapeId":"e65b6225-14f9-4d71-b8ed-245df3e04847","xaxis":2,"zaxis":-3},{"bounds":{"x":1,"y":1,"z":1},"color":"675f51","pos":{"x":-7,"y":-9,"z":19},"shapeId":"8aedf6c2-94e1-4506-89d4-a0227c552f1e","xaxis":1,"zaxis":3},{"color":"df7f00","controller":{"controllers":null,"id":39462,"joints":null,"level":6},"pos":{"x":-8,"y":-4,"z":19},"shapeId":"c394b6e8-554c-4074-a119-ab2fec55e456","xaxis":-1,"zaxis":2},{"color":"df7f00","controller":{"active":false,"controllers":[{"id":39462},{"id":39816}],"id":39461,"joints":null},"pos":{"x":-8,"y":-5,"z":20},"shapeId":"70e5729d-0706-4c28-80a2-2ab9d7e7532c","xaxis":-1,"zaxis":-3},{"color":"af0e0e","controller":{"containers":null,"controllers":null,"id":39460,"joints":null},"pos":{"x":-8,"y":-6,"z":20},"shapeId":"e1ae1714-b60c-41f9-afb9-6f916ec1f59b","xaxis":-1,"zaxis":-3},{"color":"df7f01","controller":{"audioEnabled":false,"buttonMode":true,"color":"eeeeee","colorMode":false,"controllers":[{"id":39458}],"id":39459,"joints":null,"range":1},"pos":{"x":-8,"y":-11,"z":20},"shapeId":"1d4793af-cb66-4628-804a-9d7404712643","xaxis":-1,"zaxis":-2},{"color":"df7f01","controller":{"active":false,"controllers":[{"id":39460}],"id":39458,"joints":null,"seconds":0,"ticks":1},"pos":{"x":-9,"y":-8,"z":19},"shapeId":"8f7fd0e7-c46e-4944-a414-7ce2437bb30f","xaxis":1,"zaxis":3},{"color":"df7f01","controller":{"active":false,"controllers":null,"id":39457,"joints":null,"mode":0},"pos":{"x":-9,"y":-9,"z":20},"shapeId":"9f0f56e8-2c31-4d83-996c-d00a9b296c3f","xaxis":1,"zaxis":-3},{"color":"404040","controller":{"containers":null,"controllers":null,"id":39456,"joints":null},"pos":{"x":-9,"y":-11,"z":20},"shapeId":"e65b6225-14f9-4d71-b8ed-245df3e04847","xaxis":2,"zaxis":-3},{"bounds":{"x":1,"y":1,"z":1},"color":"675f51","pos":{"x":-9,"y":-9,"z":19},"shapeId":"8aedf6c2-94e1-4506-89d4-a0227c552f1e","xaxis":1,"zaxis":3},{"color":"df7f00","controller":{"controllers":null,"id":39455,"joints":null,"level":6},"pos":{"x":-10,"y":-4,"z":19},"shapeId":"c394b6e8-554c-4074-a119-ab2fec55e456","xaxis":-1,"zaxis":2},{"color":"df7f00","controller":{"active":false,"controllers":[{"id":39455},{"id":39817}],"id":39454,"joints":null},"pos":{"x":-10,"y":-5,"z":20},"shapeId":"70e5729d-0706-4c28-80a2-2ab9d7e7532c","xaxis":-1,"zaxis":-3},{"color":"af0e0e","controller":{"containers":null,"controllers":null,"id":39453,"joints":null},"pos":{"x":-10,"y":-6,"z":20},"shapeId":"e1ae1714-b60c-41f9-afb9-6f916ec1f59b","xaxis":-1,"zaxis":-3},{"color":"df7f01","controller":{"audioEnabled":false,"buttonMode":true,"color":"eeeeee","colorMode":false,"controllers":[{"id":39451}],"id":39452,"joints":null,"range":1},"pos":{"x":-10,"y":-11,"z":20},"shapeId":"1d4793af-cb66-4628-804a-9d7404712643","xaxis":-1,"zaxis":-2},{"color":"df7f01","controller":{"active":false,"controllers":[{"id":39453}],"id":39451,"joints":null,"seconds":0,"ticks":1},"pos":{"x":-11,"y":-8,"z":19},"shapeId":"8f7fd0e7-c46e-4944-a414-7ce2437bb30f","xaxis":1,"zaxis":3},{"color":"df7f01","controller":{"active":false,"controllers":null,"id":39450,"joints":null,"mode":0},"pos":{"x":-11,"y":-9,"z":20},"shapeId":"9f0f56e8-2c31-4d83-996c-d00a9b296c3f","xaxis":1,"zaxis":-3},{"color":"404040","controller":{"containers":null,"controllers":null,"id":39449,"joints":null},"pos":{"x":-11,"y":-11,"z":20},"shapeId":"e65b6225-14f9-4d71-b8ed-245df3e04847","xaxis":2,"zaxis":-3},{"bounds":{"x":1,"y":1,"z":1},"color":"675f51","pos":{"x":-11,"y":-9,"z":19},"shapeId":"8aedf6c2-94e1-4506-89d4-a0227c552f1e","xaxis":1,"zaxis":3},{"color":"df7f00","controller":{"controllers":null,"id":39448,"joints":null,"level":6},"pos":{"x":-12,"y":-4,"z":19},"shapeId":"c394b6e8-554c-4074-a119-ab2fec55e456","xaxis":-1,"zaxis":2},{"color":"df7f00","controller":{"active":false,"controllers":[{"id":39448},{"id":39815}],"id":39447,"joints":null},"pos":{"x":-12,"y":-5,"z":20},"shapeId":"70e5729d-0706-4c28-80a2-2ab9d7e7532c","xaxis":-1,"zaxis":-3},{"color":"af0e0e","controller":{"containers":null,"controllers":null,"id":39446,"joints":null},"pos":{"x":-12,"y":-6,"z":20},"shapeId":"e1ae1714-b60c-41f9-afb9-6f916ec1f59b","xaxis":-1,"zaxis":-3},{"color":"df7f01","controller":{"audioEnabled":false,"buttonMode":true,"color":"eeeeee","colorMode":false,"controllers":[{"id":39444}],"id":39445,"joints":null,"range":1},"pos":{"x":-12,"y":-11,"z":20},"shapeId":"1d4793af-cb66-4628-804a-9d7404712643","xaxis":-1,"zaxis":-2},{"color":"df7f01","controller":{"active":false,"controllers":[{"id":39446}],"id":39444,"joints":null,"seconds":0,"ticks":1},"pos":{"x":-13,"y":-8,"z":19},"shapeId":"8f7fd0e7-c46e-4944-a414-7ce2437bb30f","xaxis":1,"zaxis":3},{"color":"df7f01","controller":{"active":false,"controllers":null,"id":39443,"joints":null,"mode":0},"pos":{"x":-13,"y":-9,"z":20},"shapeId":"9f0f56e8-2c31-4d83-996c-d00a9b296c3f","xaxis":1,"zaxis":-3},{"color":"404040","controller":{"containers":null,"controllers":null,"id":39442,"joints":null},"pos":{"x":-13,"y":-11,"z":20},"shapeId":"e65b6225-14f9-4d71-b8ed-245df3e04847","xaxis":2,"zaxis":-3},{"bounds":{"x":1,"y":1,"z":1},"color":"675f51","pos":{"x":-13,"y":-9,"z":19},"shapeId":"8aedf6c2-94e1-4506-89d4-a0227c552f1e","xaxis":1,"zaxis":3},{"color":"df7f00","controller":{"containers":null,"controllers":null,"id":39804,"joints":null},"pos":{"x":-2,"y":-9,"z":18},"shapeId":"f907144d-ae63-4e5e-bff9-f9ca413e2090","xaxis":-1,"zaxis":2},{"color":"df7f00","controller":{"containers":null,"controllers":null,"id":39803,"joints":null},"pos":{"x":-4,"y":-9,"z":18},"shapeId":"f907144d-ae63-4e5e-bff9-f9ca413e2090","xaxis":-1,"zaxis":2},{"color":"df7f00","controller":{"containers":null,"controllers":null,"id":39802,"joints":null},"pos":{"x":-6,"y":-9,"z":18},"shapeId":"f907144d-ae63-4e5e-bff9-f9ca413e2090","xaxis":-1,"zaxis":2},{"color":"df7f00","controller":{"containers":null,"controllers":null,"id":39801,"joints":null},"pos":{"x":-8,"y":-9,"z":18},"shapeId":"f907144d-ae63-4e5e-bff9-f9ca413e2090","xaxis":-1,"zaxis":2},{"color":"df7f00","controller":{"containers":null,"controllers":null,"id":39800,"joints":null},"pos":{"x":-10,"y":-9,"z":18},"shapeId":"f907144d-ae63-4e5e-bff9-f9ca413e2090","xaxis":-1,"zaxis":2},{"color":"df7f00","controller":{"containers":null,"controllers":null,"id":39799,"joints":null},"pos":{"x":-12,"y":-9,"z":18},"shapeId":"f907144d-ae63-4e5e-bff9-f9ca413e2090","xaxis":-1,"zaxis":2},{"color":"df7f00","controller":{"controllers":null,"id":39441,"joints":null,"level":6},"pos":{"x":-2,"y":-4,"z":17},"shapeId":"c394b6e8-554c-4074-a119-ab2fec55e456","xaxis":-1,"zaxis":2},{"color":"df7f00","controller":{"active":false,"controllers":[{"id":39441},{"id":39814}],"id":39440,"joints":null},"pos":{"x":-2,"y":-5,"z":18},"shapeId":"70e5729d-0706-4c28-80a2-2ab9d7e7532c","xaxis":-1,"zaxis":-3},{"color":"af0e0e","controller":{"containers":null,"controllers":null,"id":39439,"joints":null},"pos":{"x":-2,"y":-6,"z":18},"shapeId":"e1ae1714-b60c-41f9-afb9-6f916ec1f59b","xaxis":-1,"zaxis":-3},{"color":"df7f01","controller":{"audioEnabled":false,"buttonMode":true,"color":"eeeeee","colorMode":false,"controllers":[{"id":39437}],"id":39438,"joints":null,"range":1},"pos":{"x":-2,"y":-11,"z":18},"shapeId":"1d4793af-cb66-4628-804a-9d7404712643","xaxis":-1,"zaxis":-2},{"color":"df7f01","controller":{"active":false,"controllers":[{"id":39439}],"id":39437,"joints":null,"seconds":0,"ticks":1},"pos":{"x":-3,"y":-8,"z":17},"shapeId":"8f7fd0e7-c46e-4944-a414-7ce2437bb30f","xaxis":1,"zaxis":3},{"color":"df7f01","controller":{"active":false,"controllers":null,"id":39436,"joints":null,"mode":0},"pos":{"x":-3,"y":-9,"z":18},"shapeId":"9f0f56e8-2c31-4d83-996c-d00a9b296c3f","xaxis":1,"zaxis":-3},{"color":"404040","controller":{"containers":null,"controllers":null,"id":39435,"joints":null},"pos":{"x":-3,"y":-11,"z":18},"shapeId":"e65b6225-14f9-4d71-b8ed-245df3e04847","xaxis":2,"zaxis":-3},{"bounds":{"x":1,"y":1,"z":1},"color":"675f51","pos":{"x":-3,"y":-9,"z":17},"shapeId":"8aedf6c2-94e1-4506-89d4-a0227c552f1e","xaxis":1,"zaxis":3},{"color":"df7f00","controller":{"controllers":null,"id":39434,"joints":null,"level":6},"pos":{"x":-5,"y":-4,"z":17},"shapeId":"c394b6e8-554c-4074-a119-ab2fec55e456","xaxis":3,"zaxis":2},{"color":"df7f00","controller":{"active":false,"controllers":[{"id":39434},{"id":39812}],"id":39433,"joints":null},"pos":{"x":-4,"y":-5,"z":17},"shapeId":"70e5729d-0706-4c28-80a2-2ab9d7e7532c","xaxis":3,"zaxis":-1},{"color":"af0e0e","controller":{"containers":null,"controllers":null,"id":39432,"joints":null},"pos":{"x":-4,"y":-6,"z":17},"shapeId":"e1ae1714-b60c-41f9-afb9-6f916ec1f59b","xaxis":3,"zaxis":-1},{"color":"df7f01","controller":{"audioEnabled":false,"buttonMode":true,"color":"eeeeee","colorMode":false,"controllers":[{"id":39430}],"id":39431,"joints":null,"range":1},"pos":{"x":-4,"y":-11,"z":17},"shapeId":"1d4793af-cb66-4628-804a-9d7404712643","xaxis":3,"zaxis":-2},{"color":"df7f01","controller":{"active":false,"controllers":[{"id":39432}],"id":39430,"joints":null,"seconds":0,"ticks":1},"pos":{"x":-5,"y":-8,"z":18},"shapeId":"8f7fd0e7-c46e-4944-a414-7ce2437bb30f","xaxis":-3,"zaxis":1},{"color":"df7f01","controller":{"active":false,"controllers":null,"id":39429,"joints":null,"mode":0},"pos":{"x":-4,"y":-9,"z":18},"shapeId":"9f0f56e8-2c31-4d83-996c-d00a9b296c3f","xaxis":-3,"zaxis":-1},{"color":"404040","controller":{"containers":null,"controllers":null,"id":39428,"joints":null},"pos":{"x":-4,"y":-11,"z":18},"shapeId":"e65b6225-14f9-4d71-b8ed-245df3e04847","xaxis":2,"zaxis":-1},{"bounds":{"x":1,"y":1,"z":1},"color":"675f51","pos":{"x":-5,"y":-9,"z":17},"shapeId":"8aedf6c2-94e1-4506-89d4-a0227c552f1e","xaxis":1,"zaxis":3},{"color":"df7f00","controller":{"controllers":null,"id":39427,"joints":null,"level":6},"pos":{"x":-7,"y":-4,"z":18},"shapeId":"c394b6e8-554c-4074-a119-ab2fec55e456","xaxis":1,"zaxis":2},{"color":"df7f00","controller":{"active":false,"controllers":[{"id":39427},{"id":39813}],"id":39426,"joints":null},"pos":{"x":-7,"y":-5,"z":17},"shapeId":"70e5729d-0706-4c28-80a2-2ab9d7e7532c","xaxis":1,"zaxis":3},{"color":"af0e0e","controller":{"containers":null,"controllers":null,"id":39425,"joints":null},"pos":{"x":-7,"y":-6,"z":17},"shapeId":"e1ae1714-b60c-41f9-afb9-6f916ec1f59b","xaxis":1,"zaxis":3},{"color":"df7f01","controller":{"audioEnabled":false,"buttonMode":true,"color":"eeeeee","colorMode":false,"controllers":[{"id":39423}],"id":39424,"joints":null,"range":1},"pos":{"x":-7,"y":-11,"z":17},"shapeId":"1d4793af-cb66-4628-804a-9d7404712643","xaxis":1,"zaxis":-2},{"color":"df7f01","controller":{"active":false,"controllers":[{"id":39425}],"id":39423,"joints":null,"seconds":0,"ticks":1},"pos":{"x":-6,"y":-8,"z":18},"shapeId":"8f7fd0e7-c46e-4944-a414-7ce2437bb30f","xaxis":-1,"zaxis":-3},{"color":"df7f01","controller":{"active":false,"controllers":null,"id":39422,"joints":null,"mode":0},"pos":{"x":-6,"y":-9,"z":17},"shapeId":"9f0f56e8-2c31-4d83-996c-d00a9b296c3f","xaxis":-1,"zaxis":3},{"color":"404040","controller":{"containers":null,"controllers":null,"id":39421,"joints":null},"pos":{"x":-6,"y":-11,"z":17},"shapeId":"e65b6225-14f9-4d71-b8ed-245df3e04847","xaxis":2,"zaxis":3},{"bounds":{"x":1,"y":1,"z":1},"color":"675f51","pos":{"x":-7,"y":-9,"z":17},"shapeId":"8aedf6c2-94e1-4506-89d4-a0227c552f1e","xaxis":1,"zaxis":3},{"color":"df7f00","controller":{"controllers":null,"id":39420,"joints":null,"level":6},"pos":{"x":-8,"y":-4,"z":17},"shapeId":"c394b6e8-554c-4074-a119-ab2fec55e456","xaxis":-1,"zaxis":2},{"color":"df7f00","controller":{"active":false,"controllers":[{"id":39420},{"id":39816}],"id":39419,"joints":null},"pos":{"x":-8,"y":-5,"z":18},"shapeId":"70e5729d-0706-4c28-80a2-2ab9d7e7532c","xaxis":-1,"zaxis":-3},{"color":"af0e0e","controller":{"containers":null,"controllers":null,"id":39418,"joints":null},"pos":{"x":-8,"y":-6,"z":18},"shapeId":"e1ae1714-b60c-41f9-afb9-6f916ec1f59b","xaxis":-1,"zaxis":-3},{"color":"df7f01","controller":{"audioEnabled":false,"buttonMode":true,"color":"eeeeee","colorMode":false,"controllers":[{"id":39416}],"id":39417,"joints":null,"range":1},"pos":{"x":-8,"y":-11,"z":18},"shapeId":"1d4793af-cb66-4628-804a-9d7404712643","xaxis":-1,"zaxis":-2},{"color":"df7f01","controller":{"active":false,"controllers":[{"id":39418}],"id":39416,"joints":null,"seconds":0,"ticks":1},"pos":{"x":-9,"y":-8,"z":17},"shapeId":"8f7fd0e7-c46e-4944-a414-7ce2437bb30f","xaxis":1,"zaxis":3},{"color":"df7f01","controller":{"active":false,"controllers":null,"id":39415,"joints":null,"mode":0},"pos":{"x":-9,"y":-9,"z":18},"shapeId":"9f0f56e8-2c31-4d83-996c-d00a9b296c3f","xaxis":1,"zaxis":-3},{"color":"404040","controller":{"containers":null,"controllers":null,"id":39414,"joints":null},"pos":{"x":-9,"y":-11,"z":18},"shapeId":"e65b6225-14f9-4d71-b8ed-245df3e04847","xaxis":2,"zaxis":-3},{"bounds":{"x":1,"y":1,"z":1},"color":"675f51","pos":{"x":-9,"y":-9,"z":17},"shapeId":"8aedf6c2-94e1-4506-89d4-a0227c552f1e","xaxis":1,"zaxis":3},{"color":"df7f00","controller":{"controllers":null,"id":39413,"joints":null,"level":6},"pos":{"x":-10,"y":-4,"z":17},"shapeId":"c394b6e8-554c-4074-a119-ab2fec55e456","xaxis":-1,"zaxis":2},{"color":"df7f00","controller":{"active":false,"controllers":[{"id":39413},{"id":39817}],"id":39412,"joints":null},"pos":{"x":-10,"y":-5,"z":18},"shapeId":"70e5729d-0706-4c28-80a2-2ab9d7e7532c","xaxis":-1,"zaxis":-3},{"color":"af0e0e","controller":{"containers":null,"controllers":null,"id":39411,"joints":null},"pos":{"x":-10,"y":-6,"z":18},"shapeId":"e1ae1714-b60c-41f9-afb9-6f916ec1f59b","xaxis":-1,"zaxis":-3},{"color":"df7f01","controller":{"audioEnabled":false,"buttonMode":true,"color":"eeeeee","colorMode":false,"controllers":[{"id":39409}],"id":39410,"joints":null,"range":1},"pos":{"x":-10,"y":-11,"z":18},"shapeId":"1d4793af-cb66-4628-804a-9d7404712643","xaxis":-1,"zaxis":-2},{"color":"df7f01","controller":{"active":false,"controllers":[{"id":39411}],"id":39409,"joints":null,"seconds":0,"ticks":1},"pos":{"x":-11,"y":-8,"z":17},"shapeId":"8f7fd0e7-c46e-4944-a414-7ce2437bb30f","xaxis":1,"zaxis":3},{"color":"df7f01","controller":{"active":false,"controllers":null,"id":39408,"joints":null,"mode":0},"pos":{"x":-11,"y":-9,"z":18},"shapeId":"9f0f56e8-2c31-4d83-996c-d00a9b296c3f","xaxis":1,"zaxis":-3},{"color":"404040","controller":{"containers":null,"controllers":null,"id":39407,"joints":null},"pos":{"x":-11,"y":-11,"z":18},"shapeId":"e65b6225-14f9-4d71-b8ed-245df3e04847","xaxis":2,"zaxis":-3},{"bounds":{"x":1,"y":1,"z":1},"color":"675f51","pos":{"x":-11,"y":-9,"z":17},"shapeId":"8aedf6c2-94e1-4506-89d4-a0227c552f1e","xaxis":1,"zaxis":3},{"color":"df7f00","controller":{"controllers":null,"id":39406,"joints":null,"level":6},"pos":{"x":-12,"y":-4,"z":17},"shapeId":"c394b6e8-554c-4074-a119-ab2fec55e456","xaxis":-1,"zaxis":2},{"color":"df7f00","controller":{"active":false,"controllers":[{"id":39406},{"id":39815}],"id":39405,"joints":null},"pos":{"x":-12,"y":-5,"z":18},"shapeId":"70e5729d-0706-4c28-80a2-2ab9d7e7532c","xaxis":-1,"zaxis":-3},{"color":"af0e0e","controller":{"containers":null,"controllers":null,"id":39404,"joints":null},"pos":{"x":-12,"y":-6,"z":18},"shapeId":"e1ae1714-b60c-41f9-afb9-6f916ec1f59b","xaxis":-1,"zaxis":-3},{"color":"df7f01","controller":{"audioEnabled":false,"buttonMode":true,"color":"eeeeee","colorMode":false,"controllers":[{"id":39402}],"id":39403,"joints":null,"range":1},"pos":{"x":-12,"y":-11,"z":18},"shapeId":"1d4793af-cb66-4628-804a-9d7404712643","xaxis":-1,"zaxis":-2},{"color":"df7f01","controller":{"active":false,"controllers":[{"id":39404}],"id":39402,"joints":null,"seconds":0,"ticks":1},"pos":{"x":-13,"y":-8,"z":17},"shapeId":"8f7fd0e7-c46e-4944-a414-7ce2437bb30f","xaxis":1,"zaxis":3},{"color":"df7f01","controller":{"active":false,"controllers":null,"id":39401,"joints":null,"mode":0},"pos":{"x":-13,"y":-9,"z":18},"shapeId":"9f0f56e8-2c31-4d83-996c-d00a9b296c3f","xaxis":1,"zaxis":-3},{"color":"404040","controller":{"containers":null,"controllers":null,"id":39400,"joints":null},"pos":{"x":-13,"y":-11,"z":18},"shapeId":"e65b6225-14f9-4d71-b8ed-245df3e04847","xaxis":2,"zaxis":-3},{"bounds":{"x":1,"y":1,"z":1},"color":"675f51","pos":{"x":-13,"y":-9,"z":17},"shapeId":"8aedf6c2-94e1-4506-89d4-a0227c552f1e","xaxis":1,"zaxis":3},{"color":"df7f00","controller":{"containers":null,"controllers":null,"id":39798,"joints":null},"pos":{"x":-2,"y":-9,"z":16},"shapeId":"f907144d-ae63-4e5e-bff9-f9ca413e2090","xaxis":-1,"zaxis":2},{"color":"df7f00","controller":{"containers":null,"controllers":null,"id":39797,"joints":null},"pos":{"x":-4,"y":-9,"z":16},"shapeId":"f907144d-ae63-4e5e-bff9-f9ca413e2090","xaxis":-1,"zaxis":2},{"color":"df7f00","controller":{"containers":null,"controllers":null,"id":39796,"joints":null},"pos":{"x":-6,"y":-9,"z":16},"shapeId":"f907144d-ae63-4e5e-bff9-f9ca413e2090","xaxis":-1,"zaxis":2},{"color":"df7f00","controller":{"containers":null,"controllers":null,"id":39795,"joints":null},"pos":{"x":-8,"y":-9,"z":16},"shapeId":"f907144d-ae63-4e5e-bff9-f9ca413e2090","xaxis":-1,"zaxis":2},{"color":"df7f00","controller":{"containers":null,"controllers":null,"id":39794,"joints":null},"pos":{"x":-10,"y":-9,"z":16},"shapeId":"f907144d-ae63-4e5e-bff9-f9ca413e2090","xaxis":-1,"zaxis":2},{"color":"df7f00","controller":{"containers":null,"controllers":null,"id":39793,"joints":null},"pos":{"x":-12,"y":-9,"z":16},"shapeId":"f907144d-ae63-4e5e-bff9-f9ca413e2090","xaxis":-1,"zaxis":2},{"color":"df7f00","controller":{"controllers":null,"id":39399,"joints":null,"level":6},"pos":{"x":-2,"y":-4,"z":15},"shapeId":"c394b6e8-554c-4074-a119-ab2fec55e456","xaxis":-1,"zaxis":2},{"color":"df7f00","controller":{"active":false,"controllers":[{"id":39399},{"id":39814}],"id":39398,"joints":null},"pos":{"x":-2,"y":-5,"z":16},"shapeId":"70e5729d-0706-4c28-80a2-2ab9d7e7532c","xaxis":-1,"zaxis":-3},{"color":"af0e0e","controller":{"containers":null,"controllers":null,"id":39397,"joints":null},"pos":{"x":-2,"y":-6,"z":16},"shapeId":"e1ae1714-b60c-41f9-afb9-6f916ec1f59b","xaxis":-1,"zaxis":-3},{"color":"df7f01","controller":{"audioEnabled":false,"buttonMode":true,"color":"eeeeee","colorMode":false,"controllers":[{"id":39395}],"id":39396,"joints":null,"range":1},"pos":{"x":-2,"y":-11,"z":16},"shapeId":"1d4793af-cb66-4628-804a-9d7404712643","xaxis":-1,"zaxis":-2},{"color":"df7f01","controller":{"active":false,"controllers":[{"id":39397}],"id":39395,"joints":null,"seconds":0,"ticks":1},"pos":{"x":-3,"y":-8,"z":15},"shapeId":"8f7fd0e7-c46e-4944-a414-7ce2437bb30f","xaxis":1,"zaxis":3},{"color":"df7f01","controller":{"active":false,"controllers":null,"id":39394,"joints":null,"mode":0},"pos":{"x":-3,"y":-9,"z":16},"shapeId":"9f0f56e8-2c31-4d83-996c-d00a9b296c3f","xaxis":1,"zaxis":-3},{"color":"404040","controller":{"containers":null,"controllers":null,"id":39393,"joints":null},"pos":{"x":-3,"y":-11,"z":16},"shapeId":"e65b6225-14f9-4d71-b8ed-245df3e04847","xaxis":2,"zaxis":-3},{"bounds":{"x":1,"y":1,"z":1},"color":"675f51","pos":{"x":-3,"y":-9,"z":15},"shapeId":"8aedf6c2-94e1-4506-89d4-a0227c552f1e","xaxis":1,"zaxis":3},{"color":"df7f00","controller":{"controllers":null,"id":39392,"joints":null,"level":6},"pos":{"x":-4,"y":-4,"z":15},"shapeId":"c394b6e8-554c-4074-a119-ab2fec55e456","xaxis":-1,"zaxis":2},{"color":"df7f00","controller":{"active":false,"controllers":[{"id":39392},{"id":39812}],"id":39391,"joints":null},"pos":{"x":-4,"y":-5,"z":16},"shapeId":"70e5729d-0706-4c28-80a2-2ab9d7e7532c","xaxis":-1,"zaxis":-3},{"color":"af0e0e","controller":{"containers":null,"controllers":null,"id":39390,"joints":null},"pos":{"x":-4,"y":-6,"z":16},"shapeId":"e1ae1714-b60c-41f9-afb9-6f916ec1f59b","xaxis":-1,"zaxis":-3},{"color":"df7f01","controller":{"audioEnabled":false,"buttonMode":true,"color":"eeeeee","colorMode":false,"controllers":[{"id":39388}],"id":39389,"joints":null,"range":1},"pos":{"x":-4,"y":-11,"z":16},"shapeId":"1d4793af-cb66-4628-804a-9d7404712643","xaxis":-1,"zaxis":-2},{"color":"df7f01","controller":{"active":false,"controllers":[{"id":39390}],"id":39388,"joints":null,"seconds":0,"ticks":1},"pos":{"x":-5,"y":-8,"z":15},"shapeId":"8f7fd0e7-c46e-4944-a414-7ce2437bb30f","xaxis":1,"zaxis":3},{"color":"df7f01","controller":{"active":false,"controllers":null,"id":39387,"joints":null,"mode":0},"pos":{"x":-5,"y":-9,"z":16},"shapeId":"9f0f56e8-2c31-4d83-996c-d00a9b296c3f","xaxis":1,"zaxis":-3},{"color":"404040","controller":{"containers":null,"controllers":null,"id":39386,"joints":null},"pos":{"x":-5,"y":-11,"z":16},"shapeId":"e65b6225-14f9-4d71-b8ed-245df3e04847","xaxis":2,"zaxis":-3},{"bounds":{"x":1,"y":1,"z":1},"color":"675f51","pos":{"x":-5,"y":-9,"z":15},"shapeId":"8aedf6c2-94e1-4506-89d4-a0227c552f1e","xaxis":1,"zaxis":3},{"color":"df7f00","controller":{"controllers":null,"id":39385,"joints":null,"level":6},"pos":{"x":-7,"y":-4,"z":15},"shapeId":"c394b6e8-554c-4074-a119-ab2fec55e456","xaxis":3,"zaxis":2},{"color":"df7f00","controller":{"active":false,"controllers":[{"id":39385},{"id":39813}],"id":39384,"joints":null},"pos":{"x":-6,"y":-5,"z":15},"shapeId":"70e5729d-0706-4c28-80a2-2ab9d7e7532c","xaxis":3,"zaxis":-1},{"color":"af0e0e","controller":{"containers":null,"controllers":null,"id":39383,"joints":null},"pos":{"x":-6,"y":-6,"z":15},"shapeId":"e1ae1714-b60c-41f9-afb9-6f916ec1f59b","xaxis":3,"zaxis":-1},{"color":"df7f01","controller":{"audioEnabled":false,"buttonMode":true,"color":"eeeeee","colorMode":false,"controllers":[{"id":39381}],"id":39382,"joints":null,"range":1},"pos":{"x":-6,"y":-11,"z":15},"shapeId":"1d4793af-cb66-4628-804a-9d7404712643","xaxis":3,"zaxis":-2},{"color":"df7f01","controller":{"active":false,"controllers":[{"id":39383}],"id":39381,"joints":null,"seconds":0,"ticks":1},"pos":{"x":-7,"y":-8,"z":16},"shapeId":"8f7fd0e7-c46e-4944-a414-7ce2437bb30f","xaxis":-3,"zaxis":1},{"color":"df7f01","controller":{"active":false,"controllers":null,"id":39380,"joints":null,"mode":0},"pos":{"x":-6,"y":-9,"z":16},"shapeId":"9f0f56e8-2c31-4d83-996c-d00a9b296c3f","xaxis":-3,"zaxis":-1},{"color":"404040","controller":{"containers":null,"controllers":null,"id":39379,"joints":null},"pos":{"x":-6,"y":-11,"z":16},"shapeId":"e65b6225-14f9-4d71-b8ed-245df3e04847","xaxis":2,"zaxis":-1},{"bounds":{"x":1,"y":1,"z":1},"color":"675f51","pos":{"x":-7,"y":-9,"z":15},"shapeId":"8aedf6c2-94e1-4506-89d4-a0227c552f1e","xaxis":1,"zaxis":3},{"color":"df7f00","controller":{"controllers":null,"id":39378,"joints":null,"level":6},"pos":{"x":-8,"y":-4,"z":15},"shapeId":"c394b6e8-554c-4074-a119-ab2fec55e456","xaxis":-1,"zaxis":2},{"color":"df7f00","controller":{"active":false,"controllers":[{"id":39378},{"id":39816}],"id":39377,"joints":null},"pos":{"x":-8,"y":-5,"z":16},"shapeId":"70e5729d-0706-4c28-80a2-2ab9d7e7532c","xaxis":-1,"zaxis":-3},{"color":"af0e0e","controller":{"containers":null,"controllers":null,"id":39376,"joints":null},"pos":{"x":-8,"y":-6,"z":16},"shapeId":"e1ae1714-b60c-41f9-afb9-6f916ec1f59b","xaxis":-1,"zaxis":-3},{"color":"df7f01","controller":{"audioEnabled":false,"buttonMode":true,"color":"eeeeee","colorMode":false,"controllers":[{"id":39374}],"id":39375,"joints":null,"range":1},"pos":{"x":-8,"y":-11,"z":16},"shapeId":"1d4793af-cb66-4628-804a-9d7404712643","xaxis":-1,"zaxis":-2},{"color":"df7f01","controller":{"active":false,"controllers":[{"id":39376}],"id":39374,"joints":null,"seconds":0,"ticks":1},"pos":{"x":-9,"y":-8,"z":15},"shapeId":"8f7fd0e7-c46e-4944-a414-7ce2437bb30f","xaxis":1,"zaxis":3},{"color":"df7f01","controller":{"active":false,"controllers":null,"id":39373,"joints":null,"mode":0},"pos":{"x":-9,"y":-9,"z":16},"shapeId":"9f0f56e8-2c31-4d83-996c-d00a9b296c3f","xaxis":1,"zaxis":-3},{"color":"404040","controller":{"containers":null,"controllers":null,"id":39372,"joints":null},"pos":{"x":-9,"y":-11,"z":16},"shapeId":"e65b6225-14f9-4d71-b8ed-245df3e04847","xaxis":2,"zaxis":-3},{"bounds":{"x":1,"y":1,"z":1},"color":"675f51","pos":{"x":-9,"y":-9,"z":15},"shapeId":"8aedf6c2-94e1-4506-89d4-a0227c552f1e","xaxis":1,"zaxis":3},{"color":"df7f00","controller":{"controllers":null,"id":39371,"joints":null,"level":6},"pos":{"x":-11,"y":-4,"z":15},"shapeId":"c394b6e8-554c-4074-a119-ab2fec55e456","xaxis":3,"zaxis":2},{"color":"df7f00","controller":{"active":false,"controllers":[{"id":39371},{"id":39817}],"id":39370,"joints":null},"pos":{"x":-10,"y":-5,"z":15},"shapeId":"70e5729d-0706-4c28-80a2-2ab9d7e7532c","xaxis":3,"zaxis":-1},{"color":"af0e0e","controller":{"containers":null,"controllers":null,"id":39369,"joints":null},"pos":{"x":-10,"y":-6,"z":15},"shapeId":"e1ae1714-b60c-41f9-afb9-6f916ec1f59b","xaxis":3,"zaxis":-1},{"color":"df7f01","controller":{"audioEnabled":false,"buttonMode":true,"color":"eeeeee","colorMode":false,"controllers":[{"id":39367}],"id":39368,"joints":null,"range":1},"pos":{"x":-10,"y":-11,"z":15},"shapeId":"1d4793af-cb66-4628-804a-9d7404712643","xaxis":3,"zaxis":-2},{"color":"df7f01","controller":{"active":false,"controllers":[{"id":39369}],"id":39367,"joints":null,"seconds":0,"ticks":1},"pos":{"x":-11,"y":-8,"z":16},"shapeId":"8f7fd0e7-c46e-4944-a414-7ce2437bb30f","xaxis":-3,"zaxis":1},{"color":"df7f01","controller":{"active":false,"controllers":null,"id":39366,"joints":null,"mode":0},"pos":{"x":-10,"y":-9,"z":16},"shapeId":"9f0f56e8-2c31-4d83-996c-d00a9b296c3f","xaxis":-3,"zaxis":-1},{"color":"404040","controller":{"containers":null,"controllers":null,"id":39365,"joints":null},"pos":{"x":-10,"y":-11,"z":16},"shapeId":"e65b6225-14f9-4d71-b8ed-245df3e04847","xaxis":2,"zaxis":-1},{"bounds":{"x":1,"y":1,"z":1},"color":"675f51","pos":{"x":-11,"y":-9,"z":15},"shapeId":"8aedf6c2-94e1-4506-89d4-a0227c552f1e","xaxis":1,"zaxis":3},{"color":"df7f00","controller":{"controllers":null,"id":39364,"joints":null,"level":6},"pos":{"x":-12,"y":-4,"z":15},"shapeId":"c394b6e8-554c-4074-a119-ab2fec55e456","xaxis":-1,"zaxis":2},{"color":"df7f00","controller":{"active":false,"controllers":[{"id":39364},{"id":39815}],"id":39363,"joints":null},"pos":{"x":-12,"y":-5,"z":16},"shapeId":"70e5729d-0706-4c28-80a2-2ab9d7e7532c","xaxis":-1,"zaxis":-3},{"color":"af0e0e","controller":{"containers":null,"controllers":null,"id":39362,"joints":null},"pos":{"x":-12,"y":-6,"z":16},"shapeId":"e1ae1714-b60c-41f9-afb9-6f916ec1f59b","xaxis":-1,"zaxis":-3},{"color":"df7f01","controller":{"audioEnabled":false,"buttonMode":true,"color":"eeeeee","colorMode":false,"controllers":[{"id":39360}],"id":39361,"joints":null,"range":1},"pos":{"x":-12,"y":-11,"z":16},"shapeId":"1d4793af-cb66-4628-804a-9d7404712643","xaxis":-1,"zaxis":-2},{"color":"df7f01","controller":{"active":false,"controllers":[{"id":39362}],"id":39360,"joints":null,"seconds":0,"ticks":1},"pos":{"x":-13,"y":-8,"z":15},"shapeId":"8f7fd0e7-c46e-4944-a414-7ce2437bb30f","xaxis":1,"zaxis":3},{"color":"df7f01","controller":{"active":false,"controllers":null,"id":39359,"joints":null,"mode":0},"pos":{"x":-13,"y":-9,"z":16},"shapeId":"9f0f56e8-2c31-4d83-996c-d00a9b296c3f","xaxis":1,"zaxis":-3},{"color":"404040","controller":{"containers":null,"controllers":null,"id":39358,"joints":null},"pos":{"x":-13,"y":-11,"z":16},"shapeId":"e65b6225-14f9-4d71-b8ed-245df3e04847","xaxis":2,"zaxis":-3},{"bounds":{"x":1,"y":1,"z":1},"color":"675f51","pos":{"x":-13,"y":-9,"z":15},"shapeId":"8aedf6c2-94e1-4506-89d4-a0227c552f1e","xaxis":1,"zaxis":3},{"color":"df7f00","controller":{"containers":null,"controllers":null,"id":39792,"joints":null},"pos":{"x":-2,"y":-9,"z":14},"shapeId":"f907144d-ae63-4e5e-bff9-f9ca413e2090","xaxis":-1,"zaxis":2},{"color":"df7f00","controller":{"containers":null,"controllers":null,"id":39791,"joints":null},"pos":{"x":-4,"y":-9,"z":14},"shapeId":"f907144d-ae63-4e5e-bff9-f9ca413e2090","xaxis":-1,"zaxis":2},{"color":"df7f00","controller":{"containers":null,"controllers":null,"id":39790,"joints":null},"pos":{"x":-6,"y":-9,"z":14},"shapeId":"f907144d-ae63-4e5e-bff9-f9ca413e2090","xaxis":-1,"zaxis":2},{"color":"df7f00","controller":{"containers":null,"controllers":null,"id":39789,"joints":null},"pos":{"x":-8,"y":-9,"z":14},"shapeId":"f907144d-ae63-4e5e-bff9-f9ca413e2090","xaxis":-1,"zaxis":2},{"color":"df7f00","controller":{"containers":null,"controllers":null,"id":39788,"joints":null},"pos":{"x":-10,"y":-9,"z":14},"shapeId":"f907144d-ae63-4e5e-bff9-f9ca413e2090","xaxis":-1,"zaxis":2},{"color":"df7f00","controller":{"containers":null,"controllers":null,"id":39787,"joints":null},"pos":{"x":-12,"y":-9,"z":14},"shapeId":"f907144d-ae63-4e5e-bff9-f9ca413e2090","xaxis":-1,"zaxis":2},{"color":"df7f00","controller":{"controllers":null,"id":39357,"joints":null,"level":6},"pos":{"x":-3,"y":-4,"z":13},"shapeId":"c394b6e8-554c-4074-a119-ab2fec55e456","xaxis":3,"zaxis":2},{"color":"df7f00","controller":{"active":false,"controllers":[{"id":39357},{"id":39814}],"id":39356,"joints":null},"pos":{"x":-2,"y":-5,"z":13},"shapeId":"70e5729d-0706-4c28-80a2-2ab9d7e7532c","xaxis":3,"zaxis":-1},{"color":"af0e0e","controller":{"containers":null,"controllers":null,"id":39355,"joints":null},"pos":{"x":-2,"y":-6,"z":13},"shapeId":"e1ae1714-b60c-41f9-afb9-6f916ec1f59b","xaxis":3,"zaxis":-1},{"color":"df7f01","controller":{"audioEnabled":false,"buttonMode":true,"color":"eeeeee","colorMode":false,"controllers":[{"id":39353}],"id":39354,"joints":null,"range":1},"pos":{"x":-2,"y":-11,"z":13},"shapeId":"1d4793af-cb66-4628-804a-9d7404712643","xaxis":3,"zaxis":-2},{"color":"df7f01","controller":{"active":false,"controllers":[{"id":39355}],"id":39353,"joints":null,"seconds":0,"ticks":1},"pos":{"x":-3,"y":-8,"z":14},"shapeId":"8f7fd0e7-c46e-4944-a414-7ce2437bb30f","xaxis":-3,"zaxis":1},{"color":"df7f01","controller":{"active":false,"controllers":null,"id":39352,"joints":null,"mode":0},"pos":{"x":-2,"y":-9,"z":14},"shapeId":"9f0f56e8-2c31-4d83-996c-d00a9b296c3f","xaxis":-3,"zaxis":-1},{"color":"404040","controller":{"containers":null,"controllers":null,"id":39351,"joints":null},"pos":{"x":-2,"y":-11,"z":14},"shapeId":"e65b6225-14f9-4d71-b8ed-245df3e04847","xaxis":2,"zaxis":-1},{"bounds":{"x":1,"y":1,"z":1},"color":"675f51","pos":{"x":-3,"y":-9,"z":13},"shapeId":"8aedf6c2-94e1-4506-89d4-a0227c552f1e","xaxis":1,"zaxis":3},{"color":"df7f00","controller":{"controllers":null,"id":39350,"joints":null,"level":6},"pos":{"x":-4,"y":-4,"z":13},"shapeId":"c394b6e8-554c-4074-a119-ab2fec55e456","xaxis":-1,"zaxis":2},{"color":"df7f00","controller":{"active":false,"controllers":[{"id":39350},{"id":39812}],"id":39349,"joints":null},"pos":{"x":-4,"y":-5,"z":14},"shapeId":"70e5729d-0706-4c28-80a2-2ab9d7e7532c","xaxis":-1,"zaxis":-3},{"color":"af0e0e","controller":{"containers":null,"controllers":null,"id":39348,"joints":null},"pos":{"x":-4,"y":-6,"z":14},"shapeId":"e1ae1714-b60c-41f9-afb9-6f916ec1f59b","xaxis":-1,"zaxis":-3},{"color":"df7f01","controller":{"audioEnabled":false,"buttonMode":true,"color":"eeeeee","colorMode":false,"controllers":[{"id":39346}],"id":39347,"joints":null,"range":1},"pos":{"x":-4,"y":-11,"z":14},"shapeId":"1d4793af-cb66-4628-804a-9d7404712643","xaxis":-1,"zaxis":-2},{"color":"df7f01","controller":{"active":false,"controllers":[{"id":39348}],"id":39346,"joints":null,"seconds":0,"ticks":1},"pos":{"x":-5,"y":-8,"z":13},"shapeId":"8f7fd0e7-c46e-4944-a414-7ce2437bb30f","xaxis":1,"zaxis":3},{"color":"df7f01","controller":{"active":false,"controllers":null,"id":39345,"joints":null,"mode":0},"pos":{"x":-5,"y":-9,"z":14},"shapeId":"9f0f56e8-2c31-4d83-996c-d00a9b296c3f","xaxis":1,"zaxis":-3},{"color":"404040","controller":{"containers":null,"controllers":null,"id":39344,"joints":null},"pos":{"x":-5,"y":-11,"z":14},"shapeId":"e65b6225-14f9-4d71-b8ed-245df3e04847","xaxis":2,"zaxis":-3},{"bounds":{"x":1,"y":1,"z":1},"color":"675f51","pos":{"x":-5,"y":-9,"z":13},"shapeId":"8aedf6c2-94e1-4506-89d4-a0227c552f1e","xaxis":1,"zaxis":3},{"color":"df7f00","controller":{"controllers":null,"id":39343,"joints":null,"level":6},"pos":{"x":-7,"y":-4,"z":14},"shapeId":"c394b6e8-554c-4074-a119-ab2fec55e456","xaxis":1,"zaxis":2},{"color":"df7f00","controller":{"active":false,"controllers":[{"id":39343},{"id":39813}],"id":39342,"joints":null},"pos":{"x":-7,"y":-5,"z":13},"shapeId":"70e5729d-0706-4c28-80a2-2ab9d7e7532c","xaxis":1,"zaxis":3},{"color":"af0e0e","controller":{"containers":null,"controllers":null,"id":39341,"joints":null},"pos":{"x":-7,"y":-6,"z":13},"shapeId":"e1ae1714-b60c-41f9-afb9-6f916ec1f59b","xaxis":1,"zaxis":3},{"color":"df7f01","controller":{"audioEnabled":false,"buttonMode":true,"color":"eeeeee","colorMode":false,"controllers":[{"id":39339}],"id":39340,"joints":null,"range":1},"pos":{"x":-7,"y":-11,"z":13},"shapeId":"1d4793af-cb66-4628-804a-9d7404712643","xaxis":1,"zaxis":-2},{"color":"df7f01","controller":{"active":false,"controllers":[{"id":39341}],"id":39339,"joints":null,"seconds":0,"ticks":1},"pos":{"x":-6,"y":-8,"z":14},"shapeId":"8f7fd0e7-c46e-4944-a414-7ce2437bb30f","xaxis":-1,"zaxis":-3},{"color":"df7f01","controller":{"active":false,"controllers":null,"id":39338,"joints":null,"mode":0},"pos":{"x":-6,"y":-9,"z":13},"shapeId":"9f0f56e8-2c31-4d83-996c-d00a9b296c3f","xaxis":-1,"zaxis":3},{"color":"404040","controller":{"containers":null,"controllers":null,"id":39337,"joints":null},"pos":{"x":-6,"y":-11,"z":13},"shapeId":"e65b6225-14f9-4d71-b8ed-245df3e04847","xaxis":2,"zaxis":3},{"bounds":{"x":1,"y":1,"z":1},"color":"675f51","pos":{"x":-7,"y":-9,"z":13},"shapeId":"8aedf6c2-94e1-4506-89d4-a0227c552f1e","xaxis":1,"zaxis":3},{"color":"df7f00","controller":{"controllers":null,"id":39336,"joints":null,"level":6},"pos":{"x":-8,"y":-4,"z":13},"shapeId":"c394b6e8-554c-4074-a119-ab2fec55e456","xaxis":-1,"zaxis":2},{"color":"df7f00","controller":{"active":false,"controllers":[{"id":39336},{"id":39816}],"id":39335,"joints":null},"pos":{"x":-8,"y":-5,"z":14},"shapeId":"70e5729d-0706-4c28-80a2-2ab9d7e7532c","xaxis":-1,"zaxis":-3},{"color":"af0e0e","controller":{"containers":null,"controllers":null,"id":39334,"joints":null},"pos":{"x":-8,"y":-6,"z":14},"shapeId":"e1ae1714-b60c-41f9-afb9-6f916ec1f59b","xaxis":-1,"zaxis":-3},{"color":"df7f01","controller":{"audioEnabled":false,"buttonMode":true,"color":"eeeeee","colorMode":false,"controllers":[{"id":39332}],"id":39333,"joints":null,"range":1},"pos":{"x":-8,"y":-11,"z":14},"shapeId":"1d4793af-cb66-4628-804a-9d7404712643","xaxis":-1,"zaxis":-2},{"color":"df7f01","controller":{"active":false,"controllers":[{"id":39334}],"id":39332,"joints":null,"seconds":0,"ticks":1},"pos":{"x":-9,"y":-8,"z":13},"shapeId":"8f7fd0e7-c46e-4944-a414-7ce2437bb30f","xaxis":1,"zaxis":3},{"color":"df7f01","controller":{"active":false,"controllers":null,"id":39331,"joints":null,"mode":0},"pos":{"x":-9,"y":-9,"z":14},"shapeId":"9f0f56e8-2c31-4d83-996c-d00a9b296c3f","xaxis":1,"zaxis":-3},{"color":"404040","controller":{"containers":null,"controllers":null,"id":39330,"joints":null},"pos":{"x":-9,"y":-11,"z":14},"shapeId":"e65b6225-14f9-4d71-b8ed-245df3e04847","xaxis":2,"zaxis":-3},{"bounds":{"x":1,"y":1,"z":1},"color":"675f51","pos":{"x":-9,"y":-9,"z":13},"shapeId":"8aedf6c2-94e1-4506-89d4-a0227c552f1e","xaxis":1,"zaxis":3},{"color":"df7f00","controller":{"controllers":null,"id":39329,"joints":null,"level":6},"pos":{"x":-10,"y":-4,"z":13},"shapeId":"c394b6e8-554c-4074-a119-ab2fec55e456","xaxis":-1,"zaxis":2},{"color":"df7f00","controller":{"active":false,"controllers":[{"id":39329},{"id":39817}],"id":39328,"joints":null},"pos":{"x":-10,"y":-5,"z":14},"shapeId":"70e5729d-0706-4c28-80a2-2ab9d7e7532c","xaxis":-1,"zaxis":-3},{"color":"af0e0e","controller":{"containers":null,"controllers":null,"id":39327,"joints":null},"pos":{"x":-10,"y":-6,"z":14},"shapeId":"e1ae1714-b60c-41f9-afb9-6f916ec1f59b","xaxis":-1,"zaxis":-3},{"color":"df7f01","controller":{"audioEnabled":false,"buttonMode":true,"color":"eeeeee","colorMode":false,"controllers":[{"id":39325}],"id":39326,"joints":null,"range":1},"pos":{"x":-10,"y":-11,"z":14},"shapeId":"1d4793af-cb66-4628-804a-9d7404712643","xaxis":-1,"zaxis":-2},{"color":"df7f01","controller":{"active":false,"controllers":[{"id":39327}],"id":39325,"joints":null,"seconds":0,"ticks":1},"pos":{"x":-11,"y":-8,"z":13},"shapeId":"8f7fd0e7-c46e-4944-a414-7ce2437bb30f","xaxis":1,"zaxis":3},{"color":"df7f01","controller":{"active":false,"controllers":null,"id":39324,"joints":null,"mode":0},"pos":{"x":-11,"y":-9,"z":14},"shapeId":"9f0f56e8-2c31-4d83-996c-d00a9b296c3f","xaxis":1,"zaxis":-3},{"color":"404040","controller":{"containers":null,"controllers":null,"id":39323,"joints":null},"pos":{"x":-11,"y":-11,"z":14},"shapeId":"e65b6225-14f9-4d71-b8ed-245df3e04847","xaxis":2,"zaxis":-3},{"bounds":{"x":1,"y":1,"z":1},"color":"675f51","pos":{"x":-11,"y":-9,"z":13},"shapeId":"8aedf6c2-94e1-4506-89d4-a0227c552f1e","xaxis":1,"zaxis":3},{"color":"df7f00","controller":{"controllers":null,"id":39322,"joints":null,"level":6},"pos":{"x":-12,"y":-4,"z":13},"shapeId":"c394b6e8-554c-4074-a119-ab2fec55e456","xaxis":-1,"zaxis":2},{"color":"df7f00","controller":{"active":false,"controllers":[{"id":39322},{"id":39815}],"id":39321,"joints":null},"pos":{"x":-12,"y":-5,"z":14},"shapeId":"70e5729d-0706-4c28-80a2-2ab9d7e7532c","xaxis":-1,"zaxis":-3},{"color":"af0e0e","controller":{"containers":null,"controllers":null,"id":39320,"joints":null},"pos":{"x":-12,"y":-6,"z":14},"shapeId":"e1ae1714-b60c-41f9-afb9-6f916ec1f59b","xaxis":-1,"zaxis":-3},{"color":"df7f01","controller":{"audioEnabled":false,"buttonMode":true,"color":"eeeeee","colorMode":false,"controllers":[{"id":39318}],"id":39319,"joints":null,"range":1},"pos":{"x":-12,"y":-11,"z":14},"shapeId":"1d4793af-cb66-4628-804a-9d7404712643","xaxis":-1,"zaxis":-2},{"color":"df7f01","controller":{"active":false,"controllers":[{"id":39320}],"id":39318,"joints":null,"seconds":0,"ticks":1},"pos":{"x":-13,"y":-8,"z":13},"shapeId":"8f7fd0e7-c46e-4944-a414-7ce2437bb30f","xaxis":1,"zaxis":3},{"color":"df7f01","controller":{"active":false,"controllers":null,"id":39317,"joints":null,"mode":0},"pos":{"x":-13,"y":-9,"z":14},"shapeId":"9f0f56e8-2c31-4d83-996c-d00a9b296c3f","xaxis":1,"zaxis":-3},{"color":"404040","controller":{"containers":null,"controllers":null,"id":39316,"joints":null},"pos":{"x":-13,"y":-11,"z":14},"shapeId":"e65b6225-14f9-4d71-b8ed-245df3e04847","xaxis":2,"zaxis":-3},{"bounds":{"x":1,"y":1,"z":1},"color":"675f51","pos":{"x":-13,"y":-9,"z":13},"shapeId":"8aedf6c2-94e1-4506-89d4-a0227c552f1e","xaxis":1,"zaxis":3},{"color":"df7f00","controller":{"containers":null,"controllers":null,"id":39770,"joints":null},"pos":{"x":-8,"y":-9,"z":9},"shapeId":"f907144d-ae63-4e5e-bff9-f9ca413e2090","xaxis":2,"zaxis":-1},{"color":"df7f00","controller":{"containers":null,"controllers":null,"id":39769,"joints":null},"pos":{"x":-6,"y":-9,"z":9},"shapeId":"f907144d-ae63-4e5e-bff9-f9ca413e2090","xaxis":2,"zaxis":-1},{"color":"7a7a7a","joints":[{"id":7115}],"pos":{"x":-13,"y":-9,"z":7},"shapeId":"e1273b8a-945b-4080-81eb-cbf79961cccb","xaxis":1,"zaxis":3},{"color":"df7f00","controller":{"containers":null,"controllers":null,"id":39763,"joints":null},"pos":{"x":-2,"y":-9,"z":9},"shapeId":"f907144d-ae63-4e5e-bff9-f9ca413e2090","xaxis":2,"zaxis":-1},{"color":"7a7a7a","joints":[{"id":7116}],"pos":{"x":-3,"y":-9,"z":7},"shapeId":"e1273b8a-945b-4080-81eb-cbf79961cccb","xaxis":1,"zaxis":3},{"color":"7a7a7a","pos":{"x":-4,"y":-9,"z":7},"shapeId":"e1273b8a-945b-4080-81eb-cbf79961cccb","xaxis":1,"zaxis":3},{"color":"7a7a7a","pos":{"x":-5,"y":-9,"z":7},"shapeId":"e1273b8a-945b-4080-81eb-cbf79961cccb","xaxis":1,"zaxis":3},{"color":"7a7a7a","pos":{"x":-6,"y":-9,"z":7},"shapeId":"e1273b8a-945b-4080-81eb-cbf79961cccb","xaxis":1,"zaxis":3},{"color":"7a7a7a","pos":{"x":-7,"y":-9,"z":7},"shapeId":"e1273b8a-945b-4080-81eb-cbf79961cccb","xaxis":1,"zaxis":3},{"color":"7a7a7a","pos":{"x":-8,"y":-9,"z":7},"shapeId":"e1273b8a-945b-4080-81eb-cbf79961cccb","xaxis":1,"zaxis":3},{"color":"7a7a7a","pos":{"x":-9,"y":-9,"z":7},"shapeId":"e1273b8a-945b-4080-81eb-cbf79961cccb","xaxis":1,"zaxis":3},{"color":"7a7a7a","pos":{"x":-10,"y":-9,"z":7},"shapeId":"e1273b8a-945b-4080-81eb-cbf79961cccb","xaxis":1,"zaxis":3},{"color":"7a7a7a","pos":{"x":-11,"y":-9,"z":7},"shapeId":"e1273b8a-945b-4080-81eb-cbf79961cccb","xaxis":1,"zaxis":3},{"color":"7a7a7a","pos":{"x":-12,"y":-9,"z":7},"shapeId":"e1273b8a-945b-4080-81eb-cbf79961cccb","xaxis":1,"zaxis":3},{"color":"df7f00","controller":{"containers":null,"controllers":null,"id":39768,"joints":null},"pos":{"x":-4,"y":-9,"z":9},"shapeId":"f907144d-ae63-4e5e-bff9-f9ca413e2090","xaxis":2,"zaxis":-1},{"color":"df7f00","controller":{"containers":null,"controllers":null,"id":39771,"joints":null},"pos":{"x":-10,"y":-9,"z":9},"shapeId":"f907144d-ae63-4e5e-bff9-f9ca413e2090","xaxis":2,"zaxis":-1},{"color":"df7f00","controller":{"containers":null,"controllers":null,"id":39772,"joints":null},"pos":{"x":-12,"y":-9,"z":9},"shapeId":"f907144d-ae63-4e5e-bff9-f9ca413e2090","xaxis":2,"zaxis":-1},{"bounds":{"x":1,"y":1,"z":1},"color":"675f51","pos":{"x":-3,"y":-9,"z":9},"shapeId":"8aedf6c2-94e1-4506-89d4-a0227c552f1e","xaxis":1,"zaxis":3},{"color":"404040","controller":{"containers":null,"controllers":null,"id":39546,"joints":null},"pos":{"x":-3,"y":-11,"z":10},"shapeId":"e65b6225-14f9-4d71-b8ed-245df3e04847","xaxis":2,"zaxis":-3},{"color":"df7f01","controller":{"active":false,"controllers":null,"id":39547,"joints":null,"mode":0},"pos":{"x":-3,"y":-9,"z":10},"shapeId":"9f0f56e8-2c31-4d83-996c-d00a9b296c3f","xaxis":1,"zaxis":-3},{"color":"df7f01","controller":{"active":false,"controllers":[{"id":39550}],"id":39548,"joints":null,"seconds":0,"ticks":1},"pos":{"x":-3,"y":-8,"z":9},"shapeId":"8f7fd0e7-c46e-4944-a414-7ce2437bb30f","xaxis":1,"zaxis":3},{"color":"df7f01","controller":{"audioEnabled":false,"buttonMode":true,"color":"eeeeee","colorMode":false,"controllers":[{"id":39548}],"id":39549,"joints":null,"range":1},"pos":{"x":-2,"y":-11,"z":10},"shapeId":"1d4793af-cb66-4628-804a-9d7404712643","xaxis":-1,"zaxis":-2},{"color":"af0e0e","controller":{"containers":null,"controllers":null,"id":39550,"joints":null},"pos":{"x":-2,"y":-6,"z":10},"shapeId":"e1ae1714-b60c-41f9-afb9-6f916ec1f59b","xaxis":-1,"zaxis":-3},{"color":"df7f00","controller":{"active":false,"controllers":[{"id":39552},{"id":39814}],"id":39551,"joints":null},"pos":{"x":-2,"y":-5,"z":10},"shapeId":"70e5729d-0706-4c28-80a2-2ab9d7e7532c","xaxis":-1,"zaxis":-3},{"color":"df7f00","controller":{"controllers":null,"id":39552,"joints":null,"level":6},"pos":{"x":-2,"y":-4,"z":9},"shapeId":"c394b6e8-554c-4074-a119-ab2fec55e456","xaxis":-1,"zaxis":2},{"bounds":{"x":1,"y":1,"z":1},"color":"675f51","pos":{"x":-5,"y":-9,"z":9},"shapeId":"8aedf6c2-94e1-4506-89d4-a0227c552f1e","xaxis":1,"zaxis":3},{"color":"404040","controller":{"containers":null,"controllers":null,"id":39530,"joints":null},"pos":{"x":-5,"y":-11,"z":10},"shapeId":"e65b6225-14f9-4d71-b8ed-245df3e04847","xaxis":2,"zaxis":-3},{"color":"df7f01","controller":{"active":false,"controllers":null,"id":39531,"joints":null,"mode":0},"pos":{"x":-5,"y":-9,"z":10},"shapeId":"9f0f56e8-2c31-4d83-996c-d00a9b296c3f","xaxis":1,"zaxis":-3},{"color":"df7f01","controller":{"active":false,"controllers":[{"id":39534}],"id":39532,"joints":null,"seconds":0,"ticks":1},"pos":{"x":-5,"y":-8,"z":9},"shapeId":"8f7fd0e7-c46e-4944-a414-7ce2437bb30f","xaxis":1,"zaxis":3},{"color":"df7f01","controller":{"audioEnabled":false,"buttonMode":true,"color":"eeeeee","colorMode":false,"controllers":[{"id":39532}],"id":39533,"joints":null,"range":1},"pos":{"x":-4,"y":-11,"z":10},"shapeId":"1d4793af-cb66-4628-804a-9d7404712643","xaxis":-1,"zaxis":-2},{"color":"af0e0e","controller":{"containers":null,"controllers":null,"id":39534,"joints":null},"pos":{"x":-4,"y":-6,"z":10},"shapeId":"e1ae1714-b60c-41f9-afb9-6f916ec1f59b","xaxis":-1,"zaxis":-3},{"color":"df7f00","controller":{"active":false,"controllers":[{"id":39536}],"id":39535,"joints":null},"pos":{"x":-4,"y":-5,"z":10},"shapeId":"70e5729d-0706-4c28-80a2-2ab9d7e7532c","xaxis":-1,"zaxis":-3},{"color":"df7f00","controller":{"controllers":null,"id":39536,"joints":null,"level":6},"pos":{"x":-4,"y":-4,"z":9},"shapeId":"c394b6e8-554c-4074-a119-ab2fec55e456","xaxis":-1,"zaxis":2},{"bounds":{"x":1,"y":1,"z":1},"color":"675f51","pos":{"x":-7,"y":-9,"z":9},"shapeId":"8aedf6c2-94e1-4506-89d4-a0227c552f1e","xaxis":1,"zaxis":3},{"color":"404040","controller":{"containers":null,"controllers":null,"id":39523,"joints":null},"pos":{"x":-6,"y":-11,"z":10},"shapeId":"e65b6225-14f9-4d71-b8ed-245df3e04847","xaxis":2,"zaxis":-1},{"color":"df7f01","controller":{"active":false,"controllers":null,"id":39524,"joints":null,"mode":0},"pos":{"x":-6,"y":-9,"z":10},"shapeId":"9f0f56e8-2c31-4d83-996c-d00a9b296c3f","xaxis":-3,"zaxis":-1},{"color":"df7f01","controller":{"active":false,"controllers":[{"id":39527}],"id":39525,"joints":null,"seconds":0,"ticks":1},"pos":{"x":-7,"y":-8,"z":10},"shapeId":"8f7fd0e7-c46e-4944-a414-7ce2437bb30f","xaxis":-3,"zaxis":1},{"color":"df7f01","controller":{"audioEnabled":false,"buttonMode":true,"color":"eeeeee","colorMode":false,"controllers":[{"id":39525}],"id":39526,"joints":null,"range":1},"pos":{"x":-6,"y":-11,"z":9},"shapeId":"1d4793af-cb66-4628-804a-9d7404712643","xaxis":3,"zaxis":-2},{"color":"af0e0e","controller":{"containers":null,"controllers":null,"id":39527,"joints":null},"pos":{"x":-6,"y":-6,"z":9},"shapeId":"e1ae1714-b60c-41f9-afb9-6f916ec1f59b","xaxis":3,"zaxis":-1},{"color":"df7f00","controller":{"active":false,"controllers":[{"id":39529},{"id":39813}],"id":39528,"joints":null},"pos":{"x":-6,"y":-5,"z":9},"shapeId":"70e5729d-0706-4c28-80a2-2ab9d7e7532c","xaxis":3,"zaxis":-1},{"color":"df7f00","controller":{"controllers":null,"id":39529,"joints":null,"level":6},"pos":{"x":-7,"y":-4,"z":9},"shapeId":"c394b6e8-554c-4074-a119-ab2fec55e456","xaxis":3,"zaxis":2},{"bounds":{"x":1,"y":1,"z":1},"color":"675f51","pos":{"x":-9,"y":-9,"z":9},"shapeId":"8aedf6c2-94e1-4506-89d4-a0227c552f1e","xaxis":1,"zaxis":3},{"color":"404040","controller":{"containers":null,"controllers":null,"id":39516,"joints":null},"pos":{"x":-9,"y":-11,"z":10},"shapeId":"e65b6225-14f9-4d71-b8ed-245df3e04847","xaxis":2,"zaxis":-3},{"color":"df7f01","controller":{"active":false,"controllers":null,"id":39517,"joints":null,"mode":0},"pos":{"x":-9,"y":-9,"z":10},"shapeId":"9f0f56e8-2c31-4d83-996c-d00a9b296c3f","xaxis":1,"zaxis":-3},{"color":"df7f01","controller":{"active":false,"controllers":[{"id":39520}],"id":39518,"joints":null,"seconds":0,"ticks":1},"pos":{"x":-9,"y":-8,"z":9},"shapeId":"8f7fd0e7-c46e-4944-a414-7ce2437bb30f","xaxis":1,"zaxis":3},{"color":"df7f01","controller":{"audioEnabled":false,"buttonMode":true,"color":"eeeeee","colorMode":false,"controllers":[{"id":39518}],"id":39519,"joints":null,"range":1},"pos":{"x":-8,"y":-11,"z":10},"shapeId":"1d4793af-cb66-4628-804a-9d7404712643","xaxis":-1,"zaxis":-2},{"color":"af0e0e","controller":{"containers":null,"controllers":null,"id":39520,"joints":null},"pos":{"x":-8,"y":-6,"z":10},"shapeId":"e1ae1714-b60c-41f9-afb9-6f916ec1f59b","xaxis":-1,"zaxis":-3},{"color":"df7f00","controller":{"active":false,"controllers":[{"id":39522},{"id":39816}],"id":39521,"joints":null},"pos":{"x":-8,"y":-5,"z":10},"shapeId":"70e5729d-0706-4c28-80a2-2ab9d7e7532c","xaxis":-1,"zaxis":-3},{"color":"df7f00","controller":{"controllers":null,"id":39522,"joints":null,"level":6},"pos":{"x":-8,"y":-4,"z":9},"shapeId":"c394b6e8-554c-4074-a119-ab2fec55e456","xaxis":-1,"zaxis":2},{"bounds":{"x":1,"y":1,"z":1},"color":"675f51","pos":{"x":-11,"y":-9,"z":9},"shapeId":"8aedf6c2-94e1-4506-89d4-a0227c552f1e","xaxis":1,"zaxis":3},{"color":"404040","controller":{"containers":null,"controllers":null,"id":39509,"joints":null},"pos":{"x":-11,"y":-11,"z":10},"shapeId":"e65b6225-14f9-4d71-b8ed-245df3e04847","xaxis":2,"zaxis":-3},{"color":"df7f01","controller":{"active":false,"controllers":null,"id":39510,"joints":null,"mode":0},"pos":{"x":-11,"y":-9,"z":10},"shapeId":"9f0f56e8-2c31-4d83-996c-d00a9b296c3f","xaxis":1,"zaxis":-3},{"color":"df7f01","controller":{"active":false,"controllers":[{"id":39513}],"id":39511,"joints":null,"seconds":0,"ticks":1},"pos":{"x":-11,"y":-8,"z":9},"shapeId":"8f7fd0e7-c46e-4944-a414-7ce2437bb30f","xaxis":1,"zaxis":3},{"color":"df7f01","controller":{"audioEnabled":false,"buttonMode":true,"color":"eeeeee","colorMode":false,"controllers":[{"id":39511}],"id":39512,"joints":null,"range":1},"pos":{"x":-10,"y":-11,"z":10},"shapeId":"1d4793af-cb66-4628-804a-9d7404712643","xaxis":-1,"zaxis":-2},{"color":"af0e0e","controller":{"containers":null,"controllers":null,"id":39513,"joints":null},"pos":{"x":-10,"y":-6,"z":10},"shapeId":"e1ae1714-b60c-41f9-afb9-6f916ec1f59b","xaxis":-1,"zaxis":-3},{"color":"df7f00","controller":{"active":false,"controllers":[{"id":39515},{"id":39817}],"id":39514,"joints":null},"pos":{"x":-10,"y":-5,"z":10},"shapeId":"70e5729d-0706-4c28-80a2-2ab9d7e7532c","xaxis":-1,"zaxis":-3},{"color":"df7f00","controller":{"controllers":null,"id":39515,"joints":null,"level":6},"pos":{"x":-10,"y":-4,"z":9},"shapeId":"c394b6e8-554c-4074-a119-ab2fec55e456","xaxis":-1,"zaxis":2},{"bounds":{"x":1,"y":1,"z":1},"color":"675f51","pos":{"x":-13,"y":-9,"z":9},"shapeId":"8aedf6c2-94e1-4506-89d4-a0227c552f1e","xaxis":1,"zaxis":3},{"color":"404040","controller":{"containers":null,"controllers":null,"id":39502,"joints":null},"pos":{"x":-12,"y":-11,"z":10},"shapeId":"e65b6225-14f9-4d71-b8ed-245df3e04847","xaxis":2,"zaxis":-1},{"color":"df7f01","controller":{"active":false,"controllers":null,"id":39503,"joints":null,"mode":0},"pos":{"x":-12,"y":-9,"z":10},"shapeId":"9f0f56e8-2c31-4d83-996c-d00a9b296c3f","xaxis":-3,"zaxis":-1},{"color":"df7f01","controller":{"active":false,"controllers":[{"id":39506}],"id":39504,"joints":null,"seconds":0,"ticks":1},"pos":{"x":-13,"y":-8,"z":10},"shapeId":"8f7fd0e7-c46e-4944-a414-7ce2437bb30f","xaxis":-3,"zaxis":1},{"color":"df7f01","controller":{"audioEnabled":false,"buttonMode":true,"color":"eeeeee","colorMode":false,"controllers":[{"id":39504}],"id":39505,"joints":null,"range":1},"pos":{"x":-12,"y":-11,"z":9},"shapeId":"1d4793af-cb66-4628-804a-9d7404712643","xaxis":3,"zaxis":-2},{"color":"af0e0e","controller":{"containers":null,"controllers":null,"id":39506,"joints":null},"pos":{"x":-12,"y":-6,"z":9},"shapeId":"e1ae1714-b60c-41f9-afb9-6f916ec1f59b","xaxis":3,"zaxis":-1},{"color":"df7f00","controller":{"active":false,"controllers":[{"id":39508},{"id":39815}],"id":39507,"joints":null},"pos":{"x":-12,"y":-5,"z":9},"shapeId":"70e5729d-0706-4c28-80a2-2ab9d7e7532c","xaxis":3,"zaxis":-1},{"color":"df7f00","controller":{"controllers":null,"id":39508,"joints":null,"level":6},"pos":{"x":-13,"y":-4,"z":9},"shapeId":"c394b6e8-554c-4074-a119-ab2fec55e456","xaxis":3,"zaxis":2},{"color":"df7f00","controller":{"containers":null,"controllers":null,"id":39773,"joints":null},"pos":{"x":-2,"y":-9,"z":11},"shapeId":"f907144d-ae63-4e5e-bff9-f9ca413e2090","xaxis":2,"zaxis":-1},{"color":"df7f00","controller":{"containers":null,"controllers":null,"id":39774,"joints":null},"pos":{"x":-4,"y":-9,"z":11},"shapeId":"f907144d-ae63-4e5e-bff9-f9ca413e2090","xaxis":2,"zaxis":-1},{"color":"df7f00","controller":{"containers":null,"controllers":null,"id":39775,"joints":null},"pos":{"x":-6,"y":-9,"z":11},"shapeId":"f907144d-ae63-4e5e-bff9-f9ca413e2090","xaxis":2,"zaxis":-1},{"color":"df7f00","controller":{"containers":null,"controllers":null,"id":39776,"joints":null},"pos":{"x":-8,"y":-9,"z":11},"shapeId":"f907144d-ae63-4e5e-bff9-f9ca413e2090","xaxis":2,"zaxis":-1},{"color":"df7f00","controller":{"containers":null,"controllers":null,"id":39777,"joints":null},"pos":{"x":-10,"y":-9,"z":11},"shapeId":"f907144d-ae63-4e5e-bff9-f9ca413e2090","xaxis":2,"zaxis":-1},{"color":"df7f00","controller":{"containers":null,"controllers":null,"id":39778,"joints":null},"pos":{"x":-12,"y":-9,"z":11},"shapeId":"f907144d-ae63-4e5e-bff9-f9ca413e2090","xaxis":2,"zaxis":-1},{"bounds":{"x":1,"y":1,"z":1},"color":"675f51","pos":{"x":-13,"y":-9,"z":11},"shapeId":"8aedf6c2-94e1-4506-89d4-a0227c552f1e","xaxis":1,"zaxis":3},{"color":"404040","controller":{"containers":null,"controllers":null,"id":39495,"joints":null},"pos":{"x":-12,"y":-11,"z":12},"shapeId":"e65b6225-14f9-4d71-b8ed-245df3e04847","xaxis":2,"zaxis":-1},{"color":"df7f01","controller":{"active":false,"controllers":null,"id":39496,"joints":null,"mode":0},"pos":{"x":-12,"y":-9,"z":12},"shapeId":"9f0f56e8-2c31-4d83-996c-d00a9b296c3f","xaxis":-3,"zaxis":-1},{"color":"df7f01","controller":{"active":false,"controllers":[{"id":39499}],"id":39497,"joints":null,"seconds":0,"ticks":1},"pos":{"x":-13,"y":-8,"z":12},"shapeId":"8f7fd0e7-c46e-4944-a414-7ce2437bb30f","xaxis":-3,"zaxis":1},{"color":"df7f01","controller":{"audioEnabled":false,"buttonMode":true,"color":"eeeeee","colorMode":false,"controllers":[{"id":39497}],"id":39498,"joints":null,"range":1},"pos":{"x":-12,"y":-11,"z":11},"shapeId":"1d4793af-cb66-4628-804a-9d7404712643","xaxis":3,"zaxis":-2},{"color":"af0e0e","controller":{"containers":null,"controllers":null,"id":39499,"joints":null},"pos":{"x":-12,"y":-6,"z":11},"shapeId":"e1ae1714-b60c-41f9-afb9-6f916ec1f59b","xaxis":3,"zaxis":-1},{"color":"df7f00","controller":{"active":false,"controllers":[{"id":39501},{"id":39815}],"id":39500,"joints":null},"pos":{"x":-12,"y":-5,"z":11},"shapeId":"70e5729d-0706-4c28-80a2-2ab9d7e7532c","xaxis":3,"zaxis":-1},{"color":"df7f00","controller":{"controllers":null,"id":39501,"joints":null,"level":6},"pos":{"x":-13,"y":-4,"z":11},"shapeId":"c394b6e8-554c-4074-a119-ab2fec55e456","xaxis":3,"zaxis":2},{"bounds":{"x":1,"y":1,"z":1},"color":"675f51","pos":{"x":-11,"y":-9,"z":11},"shapeId":"8aedf6c2-94e1-4506-89d4-a0227c552f1e","xaxis":1,"zaxis":3},{"color":"404040","controller":{"containers":null,"controllers":null,"id":39281,"joints":null},"pos":{"x":-11,"y":-11,"z":12},"shapeId":"e65b6225-14f9-4d71-b8ed-245df3e04847","xaxis":2,"zaxis":-3},{"color":"df7f01","controller":{"active":false,"controllers":null,"id":39282,"joints":null,"mode":0},"pos":{"x":-11,"y":-9,"z":12},"shapeId":"9f0f56e8-2c31-4d83-996c-d00a9b296c3f","xaxis":1,"zaxis":-3},{"color":"df7f01","controller":{"active":false,"controllers":[{"id":39285}],"id":39283,"joints":null,"seconds":0,"ticks":1},"pos":{"x":-11,"y":-8,"z":11},"shapeId":"8f7fd0e7-c46e-4944-a414-7ce2437bb30f","xaxis":1,"zaxis":3},{"color":"df7f01","controller":{"audioEnabled":false,"buttonMode":true,"color":"eeeeee","colorMode":false,"controllers":[{"id":39283}],"id":39284,"joints":null,"range":1},"pos":{"x":-10,"y":-11,"z":12},"shapeId":"1d4793af-cb66-4628-804a-9d7404712643","xaxis":-1,"zaxis":-2},{"color":"af0e0e","controller":{"containers":null,"controllers":null,"id":39285,"joints":null},"pos":{"x":-10,"y":-6,"z":12},"shapeId":"e1ae1714-b60c-41f9-afb9-6f916ec1f59b","xaxis":-1,"zaxis":-3},{"color":"df7f00","controller":{"active":false,"controllers":[{"id":39287},{"id":39817}],"id":39286,"joints":null},"pos":{"x":-10,"y":-5,"z":12},"shapeId":"70e5729d-0706-4c28-80a2-2ab9d7e7532c","xaxis":-1,"zaxis":-3},{"color":"df7f00","controller":{"controllers":null,"id":39287,"joints":null,"level":6},"pos":{"x":-10,"y":-4,"z":11},"shapeId":"c394b6e8-554c-4074-a119-ab2fec55e456","xaxis":-1,"zaxis":2},{"bounds":{"x":1,"y":1,"z":1},"color":"675f51","pos":{"x":-9,"y":-9,"z":11},"shapeId":"8aedf6c2-94e1-4506-89d4-a0227c552f1e","xaxis":1,"zaxis":3},{"color":"404040","controller":{"containers":null,"controllers":null,"id":39288,"joints":null},"pos":{"x":-8,"y":-11,"z":12},"shapeId":"e65b6225-14f9-4d71-b8ed-245df3e04847","xaxis":2,"zaxis":-1},{"color":"df7f01","controller":{"active":false,"controllers":null,"id":39289,"joints":null,"mode":0},"pos":{"x":-8,"y":-9,"z":12},"shapeId":"9f0f56e8-2c31-4d83-996c-d00a9b296c3f","xaxis":-3,"zaxis":-1},{"color":"df7f01","controller":{"active":false,"controllers":[{"id":39292}],"id":39290,"joints":null,"seconds":0,"ticks":1},"pos":{"x":-9,"y":-8,"z":12},"shapeId":"8f7fd0e7-c46e-4944-a414-7ce2437bb30f","xaxis":-3,"zaxis":1},{"color":"df7f01","controller":{"audioEnabled":false,"buttonMode":true,"color":"eeeeee","colorMode":false,"controllers":[{"id":39290}],"id":39291,"joints":null,"range":1},"pos":{"x":-8,"y":-11,"z":11},"shapeId":"1d4793af-cb66-4628-804a-9d7404712643","xaxis":3,"zaxis":-2},{"color":"af0e0e","controller":{"containers":null,"controllers":null,"id":39292,"joints":null},"pos":{"x":-8,"y":-6,"z":11},"shapeId":"e1ae1714-b60c-41f9-afb9-6f916ec1f59b","xaxis":3,"zaxis":-1},{"color":"df7f00","controller":{"active":false,"controllers":[{"id":39294},{"id":39816}],"id":39293,"joints":null},"pos":{"x":-8,"y":-5,"z":11},"shapeId":"70e5729d-0706-4c28-80a2-2ab9d7e7532c","xaxis":3,"zaxis":-1},{"color":"df7f00","controller":{"controllers":null,"id":39294,"joints":null,"level":6},"pos":{"x":-9,"y":-4,"z":11},"shapeId":"c394b6e8-554c-4074-a119-ab2fec55e456","xaxis":3,"zaxis":2},{"bounds":{"x":1,"y":1,"z":1},"color":"675f51","pos":{"x":-7,"y":-9,"z":11},"shapeId":"8aedf6c2-94e1-4506-89d4-a0227c552f1e","xaxis":1,"zaxis":3},{"color":"404040","controller":{"containers":null,"controllers":null,"id":39295,"joints":null},"pos":{"x":-7,"y":-11,"z":12},"shapeId":"e65b6225-14f9-4d71-b8ed-245df3e04847","xaxis":2,"zaxis":-3},{"color":"df7f01","controller":{"active":false,"controllers":null,"id":39296,"joints":null,"mode":0},"pos":{"x":-7,"y":-9,"z":12},"shapeId":"9f0f56e8-2c31-4d83-996c-d00a9b296c3f","xaxis":1,"zaxis":-3},{"color":"df7f01","controller":{"active":false,"controllers":[{"id":39299}],"id":39297,"joints":null,"seconds":0,"ticks":1},"pos":{"x":-7,"y":-8,"z":11},"shapeId":"8f7fd0e7-c46e-4944-a414-7ce2437bb30f","xaxis":1,"zaxis":3},{"color":"df7f01","controller":{"audioEnabled":false,"buttonMode":true,"color":"eeeeee","colorMode":false,"controllers":[{"id":39297}],"id":39298,"joints":null,"range":1},"pos":{"x":-6,"y":-11,"z":12},"shapeId":"1d4793af-cb66-4628-804a-9d7404712643","xaxis":-1,"zaxis":-2},{"color":"af0e0e","controller":{"containers":null,"controllers":null,"id":39299,"joints":null},"pos":{"x":-6,"y":-6,"z":12},"shapeId":"e1ae1714-b60c-41f9-afb9-6f916ec1f59b","xaxis":-1,"zaxis":-3},{"color":"df7f00","controller":{"active":false,"controllers":[{"id":39301},{"id":39813}],"id":39300,"joints":null},"pos":{"x":-6,"y":-5,"z":12},"shapeId":"70e5729d-0706-4c28-80a2-2ab9d7e7532c","xaxis":-1,"zaxis":-3},{"color":"df7f00","controller":{"controllers":null,"id":39301,"joints":null,"level":6},"pos":{"x":-6,"y":-4,"z":11},"shapeId":"c394b6e8-554c-4074-a119-ab2fec55e456","xaxis":-1,"zaxis":2},{"bounds":{"x":1,"y":1,"z":1},"color":"675f51","pos":{"x":-5,"y":-9,"z":11},"shapeId":"8aedf6c2-94e1-4506-89d4-a0227c552f1e","xaxis":1,"zaxis":3},{"color":"404040","controller":{"containers":null,"controllers":null,"id":39302,"joints":null},"pos":{"x":-5,"y":-11,"z":12},"shapeId":"e65b6225-14f9-4d71-b8ed-245df3e04847","xaxis":2,"zaxis":-3},{"color":"df7f01","controller":{"active":false,"controllers":null,"id":39303,"joints":null,"mode":0},"pos":{"x":-5,"y":-9,"z":12},"shapeId":"9f0f56e8-2c31-4d83-996c-d00a9b296c3f","xaxis":1,"zaxis":-3},{"color":"df7f01","controller":{"active":false,"controllers":[{"id":39306}],"id":39304,"joints":null,"seconds":0,"ticks":1},"pos":{"x":-5,"y":-8,"z":11},"shapeId":"8f7fd0e7-c46e-4944-a414-7ce2437bb30f","xaxis":1,"zaxis":3},{"color":"df7f01","controller":{"audioEnabled":false,"buttonMode":true,"color":"eeeeee","colorMode":false,"controllers":[{"id":39304}],"id":39305,"joints":null,"range":1},"pos":{"x":-4,"y":-11,"z":12},"shapeId":"1d4793af-cb66-4628-804a-9d7404712643","xaxis":-1,"zaxis":-2},{"color":"af0e0e","controller":{"containers":null,"controllers":null,"id":39306,"joints":null},"pos":{"x":-4,"y":-6,"z":12},"shapeId":"e1ae1714-b60c-41f9-afb9-6f916ec1f59b","xaxis":-1,"zaxis":-3},{"color":"df7f00","controller":{"active":false,"controllers":[{"id":39308},{"id":39812}],"id":39307,"joints":null},"pos":{"x":-4,"y":-5,"z":12},"shapeId":"70e5729d-0706-4c28-80a2-2ab9d7e7532c","xaxis":-1,"zaxis":-3},{"color":"df7f00","controller":{"controllers":null,"id":39308,"joints":null,"level":6},"pos":{"x":-4,"y":-4,"z":11},"shapeId":"c394b6e8-554c-4074-a119-ab2fec55e456","xaxis":-1,"zaxis":2},{"bounds":{"x":1,"y":1,"z":1},"color":"675f51","pos":{"x":-3,"y":-9,"z":11},"shapeId":"8aedf6c2-94e1-4506-89d4-a0227c552f1e","xaxis":1,"zaxis":3},{"color":"404040","controller":{"containers":null,"controllers":null,"id":39309,"joints":null},"pos":{"x":-3,"y":-11,"z":12},"shapeId":"e65b6225-14f9-4d71-b8ed-245df3e04847","xaxis":2,"zaxis":-3},{"color":"df7f01","controller":{"active":false,"controllers":null,"id":39310,"joints":null,"mode":0},"pos":{"x":-3,"y":-9,"z":12},"shapeId":"9f0f56e8-2c31-4d83-996c-d00a9b296c3f","xaxis":1,"zaxis":-3},{"color":"df7f01","controller":{"active":false,"controllers":[{"id":39313}],"id":39311,"joints":null,"seconds":0,"ticks":1},"pos":{"x":-3,"y":-8,"z":11},"shapeId":"8f7fd0e7-c46e-4944-a414-7ce2437bb30f","xaxis":1,"zaxis":3},{"color":"df7f01","controller":{"audioEnabled":false,"buttonMode":true,"color":"eeeeee","colorMode":false,"controllers":[{"id":39311}],"id":39312,"joints":null,"range":1},"pos":{"x":-2,"y":-11,"z":12},"shapeId":"1d4793af-cb66-4628-804a-9d7404712643","xaxis":-1,"zaxis":-2},{"color":"af0e0e","controller":{"containers":null,"controllers":null,"id":39313,"joints":null},"pos":{"x":-2,"y":-6,"z":12},"shapeId":"e1ae1714-b60c-41f9-afb9-6f916ec1f59b","xaxis":-1,"zaxis":-3},{"color":"df7f00","controller":{"active":false,"controllers":[{"id":39315},{"id":39814}],"id":39314,"joints":null},"pos":{"x":-2,"y":-5,"z":12},"shapeId":"70e5729d-0706-4c28-80a2-2ab9d7e7532c","xaxis":-1,"zaxis":-3},{"color":"df7f00","controller":{"controllers":null,"id":39315,"joints":null,"level":6},"pos":{"x":-2,"y":-4,"z":11},"shapeId":"c394b6e8-554c-4074-a119-ab2fec55e456","xaxis":-1,"zaxis":2},{"color":"df7f00","controller":{"containers":null,"controllers":null,"id":39780,"joints":null},"pos":{"x":-12,"y":-9,"z":12},"shapeId":"f907144d-ae63-4e5e-bff9-f9ca413e2090","xaxis":-1,"zaxis":2},{"color":"df7f00","controller":{"containers":null,"controllers":null,"id":39781,"joints":null},"pos":{"x":-10,"y":-9,"z":12},"shapeId":"f907144d-ae63-4e5e-bff9-f9ca413e2090","xaxis":-1,"zaxis":2},{"color":"df7f00","controller":{"containers":null,"controllers":null,"id":39782,"joints":null},"pos":{"x":-8,"y":-9,"z":12},"shapeId":"f907144d-ae63-4e5e-bff9-f9ca413e2090","xaxis":-1,"zaxis":2},{"color":"df7f00","controller":{"containers":null,"controllers":null,"id":39783,"joints":null},"pos":{"x":-6,"y":-9,"z":12},"shapeId":"f907144d-ae63-4e5e-bff9-f9ca413e2090","xaxis":-1,"zaxis":2},{"color":"df7f00","controller":{"containers":null,"controllers":null,"id":39785,"joints":null},"pos":{"x":-4,"y":-9,"z":12},"shapeId":"f907144d-ae63-4e5e-bff9-f9ca413e2090","xaxis":-1,"zaxis":2},{"color":"df7f00","controller":{"containers":null,"controllers":null,"id":39786,"joints":null},"pos":{"x":-2,"y":-9,"z":12},"shapeId":"f907144d-ae63-4e5e-bff9-f9ca413e2090","xaxis":-1,"zaxis":2}]},{"childs":[{"color":"7a7a7a","joints":[{"id":7103}],"pos":{"x":-6,"y":-10,"z":0},"shapeId":"0dba257b-b907-4919-baaf-2fefe19f4e24","xaxis":1,"zaxis":-2},{"color":"7a7a7a","pos":{"x":-5,"y":-10,"z":0},"shapeId":"0dba257b-b907-4919-baaf-2fefe19f4e24","xaxis":1,"zaxis":-2},{"color":"7a7a7a","pos":{"x":-4,"y":-10,"z":0},"shapeId":"0dba257b-b907-4919-baaf-2fefe19f4e24","xaxis":1,"zaxis":-2},{"color":"7a7a7a","pos":{"x":-3,"y":-10,"z":0},"shapeId":"0dba257b-b907-4919-baaf-2fefe19f4e24","xaxis":1,"zaxis":-2},{"color":"df7f01","pos":{"x":-2,"y":-8,"z":-2},"shapeId":"db66f0b1-0c50-4b74-bdc7-771374204b1f","xaxis":3,"zaxis":1}]},{"childs":[{"color":"7a7a7a","joints":[{"id":7097}],"pos":{"x":-6,"y":10,"z":4},"shapeId":"0dba257b-b907-4919-baaf-2fefe19f4e24","xaxis":-3,"zaxis":2},{"color":"7a7a7a","pos":{"x":-7,"y":10,"z":3},"shapeId":"8024db09-9147-4fe3-a747-00bc30ab724b","xaxis":1,"zaxis":2},{"color":"7a7a7a","pos":{"x":-6,"y":10,"z":2},"shapeId":"8024db09-9147-4fe3-a747-00bc30ab724b","xaxis":3,"zaxis":2},{"color":"7a7a7a","pos":{"x":-5,"y":11,"z":3},"shapeId":"0dba257b-b907-4919-baaf-2fefe19f4e24","xaxis":3,"zaxis":-2},{"color":"7a7a7a","pos":{"x":-6,"y":11,"z":4},"shapeId":"8024db09-9147-4fe3-a747-00bc30ab724b","xaxis":1,"zaxis":-2},{"color":"7a7a7a","joints":[{"id":7098}],"pos":{"x":-5,"y":11,"z":5},"shapeId":"8024db09-9147-4fe3-a747-00bc30ab724b","xaxis":-3,"zaxis":-2}]}],"joints":[{"childA":40,"childB":21,"color":"df7f01","id":7096,"posA":{"x":-9,"y":10,"z":3},"posB":{"x":-9,"y":10,"z":3},"shapeId":"4a1b886b-913e-4aad-b5b6-6e41b0db23a6","xaxisA":1,"xaxisB":1,"zaxisA":-3,"zaxisB":-3},{"childA":40,"childB":439,"color":"df7f01","id":7097,"posA":{"x":-7,"y":10,"z":3},"posB":{"x":-7,"y":10,"z":3},"shapeId":"4a1b886b-913e-4aad-b5b6-6e41b0db23a6","xaxisA":1,"xaxisB":1,"zaxisA":-3,"zaxisB":-3},{"childA":444,"childB":14,"color":"df7f01","controller":{"controllers":null,"id":39215,"joints":null,"stiffnessLevel":4},"id":7098,"posA":{"x":-5,"y":10,"z":3},"posB":{"x":-5,"y":10,"z":0},"shapeId":"00284190-1484-4286-a198-b2ddef768c2e","xaxisA":1,"xaxisB":1,"zaxisA":-3,"zaxisB":-3},{"childA":26,"childB":1,"color":"df7f01","controller":{"controllers":null,"id":39216,"joints":null,"stiffnessLevel":4},"id":7099,"posA":{"x":-11,"y":10,"z":3},"posB":{"x":-11,"y":10,"z":0},"shapeId":"00284190-1484-4286-a198-b2ddef768c2e","xaxisA":1,"xaxisB":1,"zaxisA":-3,"zaxisB":-3},{"childA":1,"childB":11,"color":"df7f01","id":7100,"posA":{"x":-12,"y":10,"z":0},"posB":{"x":-12,"y":10,"z":0},"shapeId":"4a1b886b-913e-4aad-b5b6-6e41b0db23a6","xaxisA":2,"xaxisB":2,"zaxisA":-1,"zaxisB":-1},{"childA":14,"childB":96,"color":"df7f01","id":7101,"posA":{"x":-4,"y":10,"z":0},"posB":{"x":-4,"y":10,"z":0},"shapeId":"4a1b886b-913e-4aad-b5b6-6e41b0db23a6","xaxisA":2,"xaxisB":2,"zaxisA":1,"zaxisB":1},{"childA":0,"childB":15,"color":"df7f01","id":7102,"posA":{"x":-10,"y":-11,"z":0},"posB":{"x":-10,"y":-11,"z":0},"shapeId":"4a1b886b-913e-4aad-b5b6-6e41b0db23a6","xaxisA":2,"xaxisB":2,"zaxisA":-1,"zaxisB":-1},{"childA":10,"childB":434,"color":"df7f01","id":7103,"posA":{"x":-6,"y":-11,"z":0},"posB":{"x":-6,"y":-11,"z":0},"shapeId":"4a1b886b-913e-4aad-b5b6-6e41b0db23a6","xaxisA":2,"xaxisB":2,"zaxisA":1,"zaxisB":1},{"childA":62,"childB":0,"color":"df7f01","controller":{"controllers":null,"id":39217,"joints":null,"stiffnessLevel":4},"id":7104,"posA":{"x":-9,"y":-11,"z":3},"posB":{"x":-9,"y":-11,"z":0},"shapeId":"00284190-1484-4286-a198-b2ddef768c2e","xaxisA":1,"xaxisB":1,"zaxisA":-3,"zaxisB":-3},{"childA":62,"childB":10,"color":"df7f01","controller":{"controllers":null,"id":39218,"joints":null,"stiffnessLevel":4},"id":7105,"posA":{"x":-7,"y":-11,"z":3},"posB":{"x":-7,"y":-11,"z":0},"shapeId":"00284190-1484-4286-a198-b2ddef768c2e","xaxisA":1,"xaxisB":1,"zaxisA":-3,"zaxisB":-3},{"childA":54,"childB":20,"color":"df7f01","id":7106,"posA":{"x":-8,"y":-9,"z":4},"posB":{"x":-8,"y":-9,"z":4},"shapeId":"4a1b886b-913e-4aad-b5b6-6e41b0db23a6","xaxisA":1,"xaxisB":1,"zaxisA":3,"zaxisB":3},{"childA":20,"childB":7,"color":"df7f01","id":7107,"posA":{"x":-8,"y":-9,"z":5},"posB":{"x":-8,"y":-9,"z":5},"shapeId":"4a1b886b-913e-4aad-b5b6-6e41b0db23a6","xaxisA":1,"xaxisB":1,"zaxisA":3,"zaxisB":3},{"childA":3,"childB":311,"color":"df7f01","id":7115,"posA":{"x":-13,"y":-9,"z":7},"posB":{"x":-13,"y":-9,"z":7},"shapeId":"4a1b886b-913e-4aad-b5b6-6e41b0db23a6","xaxisA":2,"xaxisB":2,"zaxisA":1,"zaxisB":1},{"childA":313,"childB":-1,"color":"df7f01","id":7116,"posA":{"x":-2,"y":-9,"z":7},"posB":{"x":0,"y":0,"z":0},"shapeId":"4a1b886b-913e-4aad-b5b6-6e41b0db23a6","xaxisA":2,"xaxisB":1,"zaxisA":1,"zaxisB":3}],"version":3}
