{"bodies":[{"childs":[{"bounds":{"x":9,"y":1,"z":2},"color":"9b683a","pos":{"x":-5,"y":15,"z":-5},"shapeId":"df953d9c-234f-4ac2-af5e-f0490b223e71","xaxis":1,"zaxis":3},{"bounds":{"x":1,"y":6,"z":2},"color":"9b683a","pos":{"x":-6,"y":15,"z":-5},"shapeId":"df953d9c-234f-4ac2-af5e-f0490b223e71","xaxis":1,"zaxis":3},{"bounds":{"x":9,"y":1,"z":2},"color":"9b683a","pos":{"x":-5,"y":20,"z":-5},"shapeId":"df953d9c-234f-4ac2-af5e-f0490b223e71","xaxis":1,"zaxis":3},{"bounds":{"x":10,"y":6,"z":1},"color":"9b683a","pos":{"x":-6,"y":15,"z":-6},"shapeId":"df953d9c-234f-4ac2-af5e-f0490b223e71","xaxis":1,"zaxis":3},{"bounds":{"x":1,"y":4,"z":2},"color":"9b683a","pos":{"x":3,"y":16,"z":-5},"shapeId":"df953d9c-234f-4ac2-af5e-f0490b223e71","xaxis":1,"zaxis":3},{"color":"df7f01","controller":{"controllers":null,"id":13,"joints":null,"level":6},"pos":{"x":4,"y":17,"z":-4},"shapeId":"a736ffdf-22c1-40f2-8e40-988cab7c0559","xaxis":-3,"zaxis":1},{"color":"df7f01","controller":{"containers":null,"controllers":[{"id":13}],"id":14,"joints":null,"steering":null},"pos":{"x":1,"y":20,"z":-5},"shapeId":"ffa3a47e-fc0d-4977-802f-bd15683bbe5c","xaxis":-2,"zaxis":-1},{"color":"5f7514","pos":{"x":-2,"y":15,"z":-7},"shapeId":"d361b477-69b2-4a3a-b119-ec99a3938f5b","xaxis":-1,"zaxis":3},{"color":"5f7514","pos":{"x":4,"y":15,"z":-7},"shapeId":"d361b477-69b2-4a3a-b119-ec99a3938f5b","xaxis":-1,"zaxis":3},{"color":"5f7514","pos":{"x":0,"y":21,"z":-7},"shapeId":"d361b477-69b2-4a3a-b119-ec99a3938f5b","xaxis":1,"zaxis":3},{"color":"5f7514","pos":{"x":-6,"y":21,"z":-7},"shapeId":"d361b477-69b2-4a3a-b119-ec99a3938f5b","xaxis":1,"zaxis":3}]}],"version":3}
